peripheral/i2c_fpga/slave.v
// ============================================================================
// Module Name: i2c_slave_model
// Description: Synthesizable I2C Slave with dynamic sensor_data input.
//              Uses dedicated asynchronous flag detectors for START/STOP 
//              conditions so that `state` and registers have strictly ONE driver.
// ============================================================================
module i2c_slave_model
#(
    parameter SLAVE_ADDR = 7'h3C  // 7-bit I2C Slave Address
)
(
    input        scl,          // I2C Clock Line
    inout        sda      // I2C Data Line   // Dynamic 8-bit sensor input (Switches)
);

  reg [7:0] reg_addr;
  // Open-drain output driver for SDA
  reg sda_drive;
  assign sda = sda_drive ? 1'b0 : 1'bz;

  reg bus_ready;   // goes high once scl/sda are first seen at a clean idle '1'
                    // (masks the simulation-only X glitch before the master's
                    // own reset settles -- a real bus never starts at X)
  initial begin
    state      = 3'd0;
    bit_idx    = 3'd7;
    start_flag = 1'b0;
    stop_flag  = 1'b0;
    matched    = 1'b0;
    is_read    = 1'b0;
    sda_drive  = 1'b0;
    bus_ready  = 1'b0;
  end

  always @(posedge scl or posedge sda)
    if (scl === 1'b1 && sda === 1'b1) bus_ready <= 1'b1;

  // FSM State Encoding
  localparam ST_IDLE     = 3'd0;
  localparam ST_ADDR     = 3'd1; 
  localparam ST_ADDR_ACK = 3'd2; 
  localparam ST_WR_BYTE  = 3'd3; 
  localparam ST_WR_ACK   = 3'd4; 
  localparam ST_RD_BYTE  = 3'd5; 
  localparam ST_RD_ACK   = 3'd6; 

  reg [2:0] state;
  reg [2:0] bit_idx;      
  reg [7:0] shift_in;     
  reg [7:0] cur_read_byte;
  reg       is_read;       
  reg       matched;       

  // ==========================================================================
  // START & STOP CONDITION DETECTION (Dedicated single-driver flip-flops)
  // ==========================================================================
  reg start_flag;
  reg stop_flag;

  // Set start_flag on falling edge of SDA while SCL is high; clear when SCL goes low
  always @(negedge sda or negedge scl) begin
    if (!scl || !bus_ready)
      start_flag <= 1'b0;
    else
      start_flag <= 1'b1;
  end

  // Set stop_flag on rising edge of SDA while SCL is high; clear when SCL goes low
  always @(posedge sda or negedge scl) begin
    if (!scl || !bus_ready)
      stop_flag <= 1'b0;
    else
      stop_flag <= 1'b1;
  end

  wire start_or_stop = start_flag | stop_flag;

  // ==========================================================================
  // MAIN STATE MACHINE (Single-driver logic on posedge SCL or START/STOP async)
  // ==========================================================================
  always @(posedge scl or posedge start_or_stop) begin
    if (start_or_stop) begin
      if (stop_flag) begin
        state    <= ST_IDLE;
        bit_idx  <= 3'd7;
        matched  <= 1'b0;
      end 
      else if (start_flag) begin
        state    <= ST_ADDR;
        bit_idx  <= 3'd7;
        shift_in <= 8'h00;
        matched  <= 1'b0;
      end
    end 
    else begin
      // Synchronous SCL clock domain transitions
      case (state)
        ST_ADDR: begin
          shift_in <= {shift_in[6:0], sda};
          if (bit_idx == 3'd0) begin
            is_read  <= sda;
            matched <= ({shift_in[6:0], sda} >> 1) == SLAVE_ADDR;
            state    <= ST_ADDR_ACK;
          end
          else begin
            bit_idx  <= bit_idx - 1'b1;
          end
        end

        ST_ADDR_ACK: begin
          if (matched) begin
            if (is_read) begin
              case (reg_addr)

              8'h00: cur_read_byte <= 8'h04;
              8'h01: cur_read_byte <= 8'h10;
              8'h02: cur_read_byte <= 8'h55;
              8'h03: cur_read_byte <= 8'hAA;

              default: cur_read_byte <= 8'h00;

            endcase 
              state         <= ST_RD_BYTE;
              bit_idx       <= 3'd7;
            end
            else begin
              state   <= ST_WR_BYTE;
              bit_idx <= 3'd7;
            end
          end
          else begin
            state <= ST_IDLE;
          end
        end

        ST_WR_BYTE:
        begin
            shift_in <= {shift_in[6:0], sda};

            if (bit_idx == 0) begin
                reg_addr <= {shift_in[6:0], sda};   // Save register address
                state <= ST_WR_ACK;
            end
            else
                bit_idx <= bit_idx - 1;
        end

        ST_WR_ACK: begin
          state   <= ST_WR_BYTE;
          bit_idx <= 3'd7;
        end

        ST_RD_BYTE: begin
          if (bit_idx == 3'd0) begin
            state <= ST_RD_ACK;
          end
          else begin
            bit_idx <= bit_idx - 1'b1;
          end
        end

        ST_RD_ACK: begin
          if (sda) begin
            // Master NACK -> End of Read
            state <= ST_IDLE;
          end
          else begin
            // Master ACK -> Send next byte from live sensor_data
            // cur_read_byte <= sensor_data;
            state         <= ST_RD_BYTE;
            bit_idx       <= 3'd7;
          end
        end

        default: state <= ST_IDLE;
      endcase
    end
  end

  // ==========================================================================
  // SDA OUTPUT CONTROL (Single-driver logic on negedge SCL)
  // ==========================================================================
  always @(negedge scl or posedge start_or_stop) begin
    if (start_or_stop) begin
      sda_drive <= 1'b0; // Release line on START/STOP
    end 
    else begin
      case (state)
        ST_ADDR_ACK: sda_drive <= matched;
        ST_WR_ACK:   sda_drive <= matched;
        ST_RD_BYTE:  sda_drive <= !cur_read_byte[bit_idx];
        default:     sda_drive <= 1'b0;
      endcase
    end
  end

endmodule

peripheral/i2c_simulation/i2c.v
module i2c (
	input   clk, 
	//input   scl_hi,
    input   rst,
	input   we,
	input   phase_low,
    input   phase_high,
    input   phase_fall,
	input   phase_rise,
	input [3:0] addr,
	input [31:0] wdata,
	output reg [31:0] rdata,
	output reg scl_trig,
	output reg sda_oe,
	output reg err,
	output reg busy,
	output reg done,
	input sda_in);
	
	
	reg [6:0] slv_addr;
	reg [7:0] tx_data;
	reg [4:0] state;
	reg [6:0] slv_reg;
	reg [2:0] bit_cnt;
	reg rwbar;
	reg [7:0] shift_reg;
	//reg [7:0] byte0_reg;   // holds first byte while reading second
	//reg       rd_two;      // 1 = read 2 bytes this transaction (e.g. LM75 temp reg)
	//reg       byte_sel; 
	
	
	localparam IDLE         = 5'd0,
			   START1       = 5'd1,	
			   START2       = 5'd2,
			   SLAVE_ADDR_W = 5'd3,
			   WAIT_ACK1    = 5'd4,
			   ACK1         = 5'd5,
			   REG_ADDR     = 5'd6,
			   WAIT_ACK2    = 5'd7,
			   ACK2         = 5'd8,
			   RESTART      = 5'd9,
			   SLAVE_ADDR_R = 5'd10,
			   WAIT_ACK3    = 5'd11,
			   ACK3         = 5'd12,
			   READDATA     = 5'd13,
			   WAIT_ACK4    = 5'd14,
			   ACK4         = 5'd15,
			   STOP1        = 5'd16,
			   STOP2        = 5'd17,
			   ERROR        = 5'd18;
	
	
	
	always @(posedge clk or posedge rst)
	begin
		if(rst)
		begin
			sda_oe   <= 0;
			rdata    <= 0;
			done     <= 1'b0;
			scl_trig <= 0; 
			state    <= IDLE;
			busy     <= 0;
			err      <= 0;
			shift_reg<= 0;
			bit_cnt  <= 0;
			slv_addr <= 0;
			rwbar    <= 0;
			tx_data  <= 0;
			done     <= 0;
			//byte0_reg<= 0;
			//rd_two   <= 0;
		//	byte_sel <= 0;
		end
		else begin
			
			if (we) begin
                case (addr)
                    4'h4:  begin slv_addr <= wdata[7:1]; rwbar <= wdata[0]; //rd_two <= wdata[8] 
					       end
                    4'h8:  tx_data  <= wdata[7:0];
                    4'h0: begin
                        if (wdata[0] && !busy) begin
                            busy    <= 1'b1;
                            state   <= START1;
							err     <= 0;
							done    <= 0;
                        end
                    end
                    default: begin end
                endcase
            end
			
			if (busy) begin
				case(state)
					START1 : begin
						sda_oe <= 0;
						scl_trig <= 1'b1;
						state <= START2;
					end
					
					START2 : begin
						if(phase_high)
						begin
							sda_oe    <= 1'b1;
							shift_reg <= {slv_addr,1'b0};
							bit_cnt   <= 3'd7;
							state     <= SLAVE_ADDR_W;
						end
					end
					
					SLAVE_ADDR_W : begin
					
						if (phase_low)
						begin
							sda_oe <= ~shift_reg[7];
						end
						
						else if(phase_rise)
						begin
							shift_reg <= {shift_reg[6:0], 1'b0};
							if (bit_cnt == 3'd0) state <= WAIT_ACK1;
                            else bit_cnt <= bit_cnt - 1;
						end
						
					end
					
					WAIT_ACK1 : begin
						if(phase_low)
					     state <= ACK1;
						end
					
					ACK1 : begin
						sda_oe <= 0;
						if(phase_high) begin
							if (sda_in)
								state <= ERROR;
							else begin
								shift_reg <= tx_data;
								bit_cnt   <= 3'd7;
								state     <= REG_ADDR;
							end
						end
					end
					
					REG_ADDR : begin
					    if(phase_low)
						begin
							sda_oe <= ~shift_reg[7];
							if (bit_cnt == 3'd0) state <= WAIT_ACK2;
                            else bit_cnt <= bit_cnt - 1;
						end
						else if(phase_rise)
						begin
							shift_reg <= {shift_reg[6:0], 1'b0};
							
						end
						
					end
					
					WAIT_ACK2 : begin
						if(phase_low)
					     state <= ACK2;
						end
					
					ACK2 : begin
					    sda_oe <= 0;
						if(phase_high)
						   state <= sda_in ? ERROR :RESTART;
						end

					// RESTART1 :
					// begin
					// 	if(phase_high)
					// 	begin
					// 		// Generate repeated START only
					// 		sda_oe <= 1'b1;
					// 		state  <= RESTART2;
					// 	end
					// end
					
					// RESTART2 :
					// begin
					// 	if(phase_low)
					// 	begin
					// 		shift_reg <= {slv_addr,rwbar};
					// 		bit_cnt   <= 3'd7;
					// 		state     <= SLAVE_ADDR_R;
					// 	end
					// end

					RESTART : begin
						if(phase_high)
						begin
							sda_oe    <= 1'b1;
							shift_reg <= {slv_addr,rwbar};
							bit_cnt   <= 3'd7;
							state     <= SLAVE_ADDR_R;
						end
					end
					
					SLAVE_ADDR_R : begin
						
						if (phase_low)
						begin
							sda_oe <= ~shift_reg[7];
							if (bit_cnt == 3'd0) state <= WAIT_ACK3;
                            else bit_cnt <= bit_cnt - 1;
						end
						else if(phase_rise)
						begin
							shift_reg <= {shift_reg[6:0], 1'b0};
							
						end
					end
					
					WAIT_ACK3 : begin
						if(phase_low)
					     state <= ACK3;
						end
					
					ACK3 : begin
						sda_oe <= 1'b0;
						if(phase_high)
						begin
						   state <= sda_in ? ERROR :READDATA;
						   bit_cnt <= 3'd7;
						   //byte_sel <= 1'b0;
						end
					end
					
					READDATA : begin
					    if(phase_low)
						begin
						    shift_reg <= {shift_reg[6:0], sda_in};
							if (bit_cnt == 3'd0) state <= WAIT_ACK4;
                            else bit_cnt <= bit_cnt - 1;
						end
					end
					
					WAIT_ACK4 : begin
						if(phase_low)
					     state <= ACK4;
						end
						
					ACK4 : begin
						//if (phase_low)
							sda_oe <= 1'b0;   // Release SDA = NACK

						if (phase_high) begin
							rdata <= {24'd0, shift_reg};
							state <= STOP1;
						end

					end
			
				/*	ACK4 : begin
						if (rd_two && !byte_sel) begin
							sda_oe <= 1'b1;          // drive ACK -- more bytes coming
							if (phase_high) begin
								byte0_reg <= shift_reg;
								bit_cnt   <= 3'd7;
								byte_sel  <= 1'b1;
								state     <= READDATA;  // go read the second byte
							end
						end else begin
							sda_oe <= 1'b0;           // release SDA = NACK (final byte)
							if (phase_high) begin
								rdata <= rd_two ? {16'd0, byte0_reg, shift_reg}
								                : {24'd0, shift_reg};
								state <= STOP1;
							end
						end
					end */
				
			        STOP1 : begin
						if(phase_rise)
							sda_oe <= 1;
						else if (phase_high)
						begin
							state <= STOP2;
							sda_oe <= 0;
						end
					end
					
					STOP2 : begin
						if (phase_high)
						begin
							busy  <= 1'b0;
							done  <= 1'b1; 
							state <= IDLE;
							scl_trig <= 0;
						end
					end
					
					ERROR : begin
						err <= 1;
						sda_oe <= 1'b0;
						state <= STOP1;
					end
				default : state <= IDLE;
			endcase
		    end
		end
	end
endmodule

peripheral/i2c_simulation/scl_gen1.v



`timescale 1ns / 1ps
//////////////////////////////////////////////////////////////////////////////////
// Company: 
// Engineer: 
// 
// Create Date: 23.03.2026 20:41:05
// Design Name: 
// Module Name: scl generator 
// Project Name: 
// Target Devices: 
// Tool Versions: 
// Description: 
// 
// Dependencies: 
// 
// Revision:
// Revision 0.01 - File Created
// Additional Comments:
// 
//////////////////////////////////////////////////////////////////////////////////


module scl_gen 
(
   input  wire  clk,rst,
   output wire  output_scl,
                phase_fall,
                phase_low,
                phase_rise,
                phase_high,
				scl_fsm
				//scl_hi
);
parameter CLK_FREQUENCY = 100_000_000 ;
parameter SCL_FREQUENCY = 400_000;
parameter DIVIDER       = (CLK_FREQUENCY/SCL_FREQUENCY)/4; // 62.5 cycles the clock frequency is divided rounded to 62 
parameter divider_bits  = $clog2(DIVIDER);  // 6 bits width 

reg [1:0] phase;
reg [(divider_bits-1):0] count_400hz_62cycles; // 6 bit width register for counting 62 clock cycles 
reg scl_enable ;

wire count_trigger = (count_400hz_62cycles == (DIVIDER-1)) ;

always@(posedge clk or posedge rst )
begin
   if (rst)
   begin
      count_400hz_62cycles <= 0;
      scl_enable           <= 0;
      phase                <= 2'd3;
   end
   else if (scl_fsm)
   begin
      if (count_trigger)
      begin
         count_400hz_62cycles <= {divider_bits{1'b0}};
         phase                <= (phase == 2'd3) ? 2'b0 : phase +1'b1;
      end
      else  
         count_400hz_62cycles <= count_400hz_62cycles + 1'b1;

      if (phase_fall)
         scl_enable <= 1'b1;
      else if (phase_rise)
         scl_enable <= 1'b0;

   end
   else 
   begin
      scl_enable <= 1'b0;
      phase      <= 2'd3;   // ← reset to phase_high so first active phase is high
      count_400hz_62cycles <= 0;
   end
   
end
   assign phase_fall = (phase == 2'd0 && count_trigger);
   assign phase_low  = (phase == 2'd1 && count_trigger);
   assign phase_rise = (phase == 2'd2 && count_trigger);
   assign phase_high = (phase == 2'd3 && count_trigger);
   assign output_scl = scl_enable ? 1'b0 : 1'bz;
  // assign scl_hi     = scl_enable ? 1'b0 : 1'b1;
endmodule

peripheral/i2c_simulation/i2c_top.v
module i2c_top #(
    parameter SLAVE_ADDR = 7'h3C
) (
	input   clk, 
    input   rst,
	input   we,
	input [3:0] addr,
	input [31:0] wdata,
	output [31:0] rdata,
	inout sda,
	inout scl,
	output err,
	output done,
	output busy);
	
	wire scl_trig,phase_fall,phase_low,
		 phase_rise,phase_high,sda_oe,sda_in;
	
	
    scl_gen scl_block
	   (
		  .clk(clk),
		  .rst(rst),
		  .scl_fsm(scl_trig),
		  .output_scl(scl),
		  //.scl_hi(scl_hi),
		  .phase_fall(phase_fall),
		  .phase_low(phase_low),
		  .phase_rise(phase_rise),
		  .phase_high(phase_high)
	   );
	   
			 i2c i2c_block(
			.clk(clk),
			.rst(rst),
			.we(we),
			.phase_fall(phase_fall),
			.phase_low(phase_low),
			.phase_rise(phase_rise),
			.phase_high(phase_high),
			.addr(addr),
			.wdata(wdata),
			.rdata(rdata),
			.scl_trig(scl_trig),
			.sda_oe(sda_oe),
			.err(err),
			.busy(busy),
			.done(done),
			.sda_in(sda_in));

		
	
	
	    assign sda = sda_oe ? 1'b0:1'bz;
		assign sda_in = sda;

endmodule

peripheral/i2c_simulation/i2c_top_tb.v
`timescale 1ns/1ps
module tb_probe;
    reg clk = 0;
    reg rst = 1;
    reg we = 0;
    reg [3:0] addr = 0;
    reg [31:0] wdata = 0;
    wire [31:0] rdata;
    wire err, busy;
    wire sda, scl;
	wire done;

    pullup(sda);
     pullup(scl);

    i2c_top dut(
        .clk(clk), .rst(rst), .we(we), .addr(addr), .wdata(wdata),
        .rdata(rdata),.err(err), .busy(busy),.done(done),.sda(sda),.scl(scl)
    );

    parameter SLAVE_ADDR = 7'h3C;
     i2c_slave_model #(
        .SLAVE_ADDR(SLAVE_ADDR)
    )  slave (
        .scl(scl),
        .sda(sda)
    );

    reg [13*8:1] state;  

    always #5 clk = ~clk;

    integer toggles;
    initial toggles = 0;
    always @(scl) toggles = toggles + 1;

     always @(dut.i2c_block.state)
		case(dut.i2c_block.state)
			5'b000 : state = "IDLE";
			5'b001 : state = "START1";
			5'b010 : state = "START2";
			5'b011 : state = "SLAVE_ADDR_W";
			5'b100 : state = "WAIT_ACK1";
			5'b101 : state = "ACK1";
			5'b110 : state = "REG_ADDR";
			5'b111 : state = "WAIT_ACK2";
            5'd8   : state = "ACK2";
            5'd9   : state = "RESTART";
            5'd10  : state = "SLAVE_ADDR_R";
            5'd11  : state = "WAIT_ACK3";
            5'd12  : state = "ACK3";
            5'd13  : state = "READDATA";
            5'd14  : state = "WAIT_ACK4";
            5'd15  : state = "ACK4";
            5'd16  : state = "STOP1";
            5'd17  : state = "STOP2";
            5'd18  : state = "ERROR";


			default : state = "IDLE";
		endcase

    initial begin
        #20 rst = 0;
        #20;
        // set slave addr = 7'h50, write op (rwbar=0)
        @(posedge clk); we=1; addr=7'h4; wdata = {24'd0, 7'h3C, 1'b1}; @(posedge clk); we=0;
        // set tx_data (register pointer) = 8'hA0
        @(posedge clk); we=1; addr=7'h8; wdata = 32'h00000002; @(posedge clk); we=0;
        // kick off transaction
        @(posedge clk); we=1; addr=7'h0; wdata = 32'h1; @(posedge clk); we=0;

        // Run for a generous window and report state
        #200000;
        $display("TIME=%0t busy=%b err=%b done = %0b scl_toggle_count=%0d rdata=%h", $time, busy, err, done,toggles, rdata);
        if (busy)
            $display("RESULT: STUCK - busy never cleared, transaction never completed");
        if (toggles == 0)
            $display("RESULT: SCL NEVER TOGGLED - clock generator never activated");
        $finish;
    end
    

    initial begin
        $dumpfile("i2c_top_tb.vcd");
        $dumpvars(0, tb_probe);
    end
endmodule

peripheral/i2c_simulation/i2c_top_tb.vcd
$date
	Fri Jul 31 13:55:59 2026
$end
$version
	Icarus Verilog
$end
$timescale
	1ps
$end
$scope module tb_probe $end
$var wire 1 ! scl $end
$var wire 1 " sda $end
$var wire 32 # rdata [31:0] $end
$var wire 1 $ err $end
$var wire 1 % done $end
$var wire 1 & busy $end
$var parameter 7 ' SLAVE_ADDR $end
$var reg 4 ( addr [3:0] $end
$var reg 1 ) clk $end
$var reg 1 * rst $end
$var reg 104 + state [104:1] $end
$var reg 32 , wdata [31:0] $end
$var reg 1 - we $end
$var integer 32 . toggles [31:0] $end
$scope module dut $end
$var wire 4 / addr [3:0] $end
$var wire 1 ) clk $end
$var wire 1 * rst $end
$var wire 1 ! scl $end
$var wire 1 " sda $end
$var wire 1 0 sda_in $end
$var wire 32 1 wdata [31:0] $end
$var wire 1 - we $end
$var wire 1 2 sda_oe $end
$var wire 1 3 scl_trig $end
$var wire 32 4 rdata [31:0] $end
$var wire 1 5 phase_rise $end
$var wire 1 6 phase_low $end
$var wire 1 7 phase_high $end
$var wire 1 8 phase_fall $end
$var wire 1 $ err $end
$var wire 1 % done $end
$var wire 1 & busy $end
$var parameter 7 9 SLAVE_ADDR $end
$scope module i2c_block $end
$var wire 4 : addr [3:0] $end
$var wire 1 ) clk $end
$var wire 1 * rst $end
$var wire 1 0 sda_in $end
$var wire 32 ; wdata [31:0] $end
$var wire 1 - we $end
$var wire 1 5 phase_rise $end
$var wire 1 6 phase_low $end
$var wire 1 7 phase_high $end
$var wire 1 8 phase_fall $end
$var parameter 5 < ACK1 $end
$var parameter 5 = ACK2 $end
$var parameter 5 > ACK3 $end
$var parameter 5 ? ACK4 $end
$var parameter 5 @ ERROR $end
$var parameter 5 A IDLE $end
$var parameter 5 B READDATA $end
$var parameter 5 C REG_ADDR $end
$var parameter 5 D RESTART $end
$var parameter 5 E SLAVE_ADDR_R $end
$var parameter 5 F SLAVE_ADDR_W $end
$var parameter 5 G START1 $end
$var parameter 5 H START2 $end
$var parameter 5 I STOP1 $end
$var parameter 5 J STOP2 $end
$var parameter 5 K WAIT_ACK1 $end
$var parameter 5 L WAIT_ACK2 $end
$var parameter 5 M WAIT_ACK3 $end
$var parameter 5 N WAIT_ACK4 $end
$var reg 3 O bit_cnt [2:0] $end
$var reg 1 & busy $end
$var reg 1 % done $end
$var reg 1 $ err $end
$var reg 32 P rdata [31:0] $end
$var reg 1 Q rwbar $end
$var reg 1 3 scl_trig $end
$var reg 1 2 sda_oe $end
$var reg 8 R shift_reg [7:0] $end
$var reg 7 S slv_addr [6:0] $end
$var reg 5 T state [4:0] $end
$var reg 8 U tx_data [7:0] $end
$upscope $end
$scope module scl_block $end
$var wire 1 ) clk $end
$var wire 1 ! output_scl $end
$var wire 1 8 phase_fall $end
$var wire 1 7 phase_high $end
$var wire 1 6 phase_low $end
$var wire 1 5 phase_rise $end
$var wire 1 * rst $end
$var wire 1 3 scl_fsm $end
$var wire 1 V count_trigger $end
$var parameter 32 W CLK_FREQUENCY $end
$var parameter 32 X DIVIDER $end
$var parameter 32 Y SCL_FREQUENCY $end
$var parameter 32 Z divider_bits $end
$var reg 6 [ count_400hz_62cycles [5:0] $end
$var reg 2 \ phase [1:0] $end
$var reg 1 ] scl_enable $end
$upscope $end
$upscope $end
$scope module slave $end
$var wire 1 ! scl $end
$var wire 1 " sda $end
$var wire 1 ^ start_or_stop $end
$var parameter 7 _ SLAVE_ADDR $end
$var parameter 3 ` ST_ADDR $end
$var parameter 3 a ST_ADDR_ACK $end
$var parameter 3 b ST_IDLE $end
$var parameter 3 c ST_RD_ACK $end
$var parameter 3 d ST_RD_BYTE $end
$var parameter 3 e ST_WR_ACK $end
$var parameter 3 f ST_WR_BYTE $end
$var reg 3 g bit_idx [2:0] $end
$var reg 1 h bus_ready $end
$var reg 8 i cur_read_byte [7:0] $end
$var reg 1 j is_read $end
$var reg 1 k matched $end
$var reg 8 l reg_addr [7:0] $end
$var reg 1 m sda_drive $end
$var reg 8 n shift_in [7:0] $end
$var reg 1 o start_flag $end
$var reg 3 p state [2:0] $end
$var reg 1 q stop_flag $end
$upscope $end
$upscope $end
$enddefinitions $end
$comment Show the parameter values. $end
$dumpall
b11 f
b100 e
b101 d
b110 c
b0 b
b10 a
b1 `
b111100 _
b110 Z
b1100001101010000000 Y
b111110 X
b101111101011110000100000000 W
b1110 N
b1011 M
b111 L
b100 K
b10001 J
b10000 I
b10 H
b1 G
b11 F
b1010 E
b1001 D
b110 C
b1101 B
b0 A
b10010 @
b1111 ?
b1100 >
b1000 =
b101 <
b111100 9
b111100 '
$end
#0
$dumpvars
0q
b0 p
0o
bx n
0m
bx l
0k
0j
bx i
1h
b111 g
0^
0]
b11 \
b0 [
0V
b0 U
b0 T
b0 S
b0 R
0Q
b0 P
b0 O
b0 ;
b0 :
08
07
06
05
b0 4
03
02
b0 1
10
b0 /
b11 .
0-
b0 ,
b1001001010001000100110001000101 +
1*
0)
b0 (
0&
0%
0$
b0 #
1"
1!
$end
#5000
1)
#10000
0)
#15000
1)
#20000
0)
0*
#25000
1)
#30000
0)
#35000
1)
#40000
0)
#45000
1Q
b111100 S
b1111001 ,
b1111001 1
b1111001 ;
b100 (
b100 /
b100 :
1-
1)
#50000
0)
#55000
0-
1)
#60000
0)
#65000
b10 U
b10 ,
b10 1
b10 ;
b1000 (
b1000 /
b1000 :
1-
1)
#70000
0)
#75000
0-
1)
#80000
0)
#85000
b10100110101010001000001010100100101010000110001 +
b1 T
1&
b1 ,
b1 1
b1 ;
b0 (
b0 /
b0 :
1-
1)
#90000
0)
#95000
b10100110101010001000001010100100101010000110010 +
b10 T
13
0-
1)
#100000
0)
#105000
b1 [
1)
#110000
0)
#115000
b10 [
1)
#120000
0)
#125000
b11 [
1)
#130000
0)
#135000
b100 [
1)
#140000
0)
#145000
b101 [
1)
#150000
0)
#155000
b110 [
1)
#160000
0)
#165000
b111 [
1)
#170000
0)
#175000
b1000 [
1)
#180000
0)
#185000
b1001 [
1)
#190000
0)
#195000
b1010 [
1)
#200000
0)
#205000
b1011 [
1)
#210000
0)
#215000
b1100 [
1)
#220000
0)
#225000
b1101 [
1)
#230000
0)
#235000
b1110 [
1)
#240000
0)
#245000
b1111 [
1)
#250000
0)
#255000
b10000 [
1)
#260000
0)
#265000
b10001 [
1)
#270000
0)
#275000
b10010 [
1)
#280000
0)
#285000
b10011 [
1)
#290000
0)
#295000
b10100 [
1)
#300000
0)
#305000
b10101 [
1)
#310000
0)
#315000
b10110 [
1)
#320000
0)
#325000
b10111 [
1)
#330000
0)
#335000
b11000 [
1)
#340000
0)
#345000
b11001 [
1)
#350000
0)
#355000
b11010 [
1)
#360000
0)
#365000
b11011 [
1)
#370000
0)
#375000
b11100 [
1)
#380000
0)
#385000
b11101 [
1)
#390000
0)
#395000
b11110 [
1)
#400000
0)
#405000
b11111 [
1)
#410000
0)
#415000
b100000 [
1)
#420000
0)
#425000
b100001 [
1)
#430000
0)
#435000
b100010 [
1)
#440000
0)
#445000
b100011 [
1)
#450000
0)
#455000
b100100 [
1)
#460000
0)
#465000
b100101 [
1)
#470000
0)
#475000
b100110 [
1)
#480000
0)
#485000
b100111 [
1)
#490000
0)
#495000
b101000 [
1)
#500000
0)
#505000
b101001 [
1)
#510000
0)
#515000
b101010 [
1)
#520000
0)
#525000
b101011 [
1)
#530000
0)
#535000
b101100 [
1)
#540000
0)
#545000
b101101 [
1)
#550000
0)
#555000
b101110 [
1)
#560000
0)
#565000
b101111 [
1)
#570000
0)
#575000
b110000 [
1)
#580000
0)
#585000
b110001 [
1)
#590000
0)
#595000
b110010 [
1)
#600000
0)
#605000
b110011 [
1)
#610000
0)
#615000
b110100 [
1)
#620000
0)
#625000
b110101 [
1)
#630000
0)
#635000
b110110 [
1)
#640000
0)
#645000
b110111 [
1)
#650000
0)
#655000
b111000 [
1)
#660000
0)
#665000
b111001 [
1)
#670000
0)
#675000
b111010 [
1)
#680000
0)
#685000
b111011 [
1)
#690000
0)
#695000
b111100 [
1)
#700000
0)
#705000
17
1V
b111101 [
1)
#710000
0)
#715000
b0 n
b1 p
1^
1o
07
b10100110100110001000001010101100100010101011111010000010100010001000100010100100101111101010111 +
00
0"
b0 \
0V
b0 [
b11 T
b111 O
b1111000 R
12
1)
#720000
0)
#725000
b1 [
1)
#730000
0)
#735000
b10 [
1)
#740000
0)
#745000
b11 [
1)
#750000
0)
#755000
b100 [
1)
#760000
0)
#765000
b101 [
1)
#770000
0)
#775000
b110 [
1)
#780000
0)
#785000
b111 [
1)
#790000
0)
#795000
b1000 [
1)
#800000
0)
#805000
b1001 [
1)
#810000
0)
#815000
b1010 [
1)
#820000
0)
#825000
b1011 [
1)
#830000
0)
#835000
b1100 [
1)
#840000
0)
#845000
b1101 [
1)
#850000
0)
#855000
b1110 [
1)
#860000
0)
#865000
b1111 [
1)
#870000
0)
#875000
b10000 [
1)
#880000
0)
#885000
b10001 [
1)
#890000
0)
#895000
b10010 [
1)
#900000
0)
#905000
b10011 [
1)
#910000
0)
#915000
b10100 [
1)
#920000
0)
#925000
b10101 [
1)
#930000
0)
#935000
b10110 [
1)
#940000
0)
#945000
b10111 [
1)
#950000
0)
#955000
b11000 [
1)
#960000
0)
#965000
b11001 [
1)
#970000
0)
#975000
b11010 [
1)
#980000
0)
#985000
b11011 [
1)
#990000
0)
#995000
b11100 [
1)
#1000000
0)
#1005000
b11101 [
1)
#1010000
0)
#1015000
b11110 [
1)
#1020000
0)
#1025000
b11111 [
1)
#1030000
0)
#1035000
b100000 [
1)
#1040000
0)
#1045000
b100001 [
1)
#1050000
0)
#1055000
b100010 [
1)
#1060000
0)
#1065000
b100011 [
1)
#1070000
0)
#1075000
b100100 [
1)
#1080000
0)
#1085000
b100101 [
1)
#1090000
0)
#1095000
b100110 [
1)
#1100000
0)
#1105000
b100111 [
1)
#1110000
0)
#1115000
b101000 [
1)
#1120000
0)
#1125000
b101001 [
1)
#1130000
0)
#1135000
b101010 [
1)
#1140000
0)
#1145000
b101011 [
1)
#1150000
0)
#1155000
b101100 [
1)
#1160000
0)
#1165000
b101101 [
1)
#1170000
0)
#1175000
b101110 [
1)
#1180000
0)
#1185000
b101111 [
1)
#1190000
0)
#1195000
b110000 [
1)
#1200000
0)
#1205000
b110001 [
1)
#1210000
0)
#1215000
b110010 [
1)
#1220000
0)
#1225000
b110011 [
1)
#1230000
0)
#1235000
b110100 [
1)
#1240000
0)
#1245000
b110101 [
1)
#1250000
0)
#1255000
b110110 [
1)
#1260000
0)
#1265000
b110111 [
1)
#1270000
0)
#1275000
b111000 [
1)
#1280000
0)
#1285000
b111001 [
1)
#1290000
0)
#1295000
b111010 [
1)
#1300000
0)
#1305000
b111011 [
1)
#1310000
0)
#1315000
b111100 [
1)
#1320000
0)
#1325000
18
1V
b111101 [
1)
#1330000
0)
#1335000
0^
0o
b100 .
0!
08
1]
b1 \
0V
b0 [
1)
#1340000
0)
#1345000
b1 [
1)
#1350000
0)
#1355000
b10 [
1)
#1360000
0)
#1365000
b11 [
1)
#1370000
0)
#1375000
b100 [
1)
#1380000
0)
#1385000
b101 [
1)
#1390000
0)
#1395000
b110 [
1)
#1400000
0)
#1405000
b111 [
1)
#1410000
0)
#1415000
b1000 [
1)
#1420000
0)
#1425000
b1001 [
1)
#1430000
0)
#1435000
b1010 [
1)
#1440000
0)
#1445000
b1011 [
1)
#1450000
0)
#1455000
b1100 [
1)
#1460000
0)
#1465000
b1101 [
1)
#1470000
0)
#1475000
b1110 [
1)
#1480000
0)
#1485000
b1111 [
1)
#1490000
0)
#1495000
b10000 [
1)
#1500000
0)
#1505000
b10001 [
1)
#1510000
0)
#1515000
b10010 [
1)
#1520000
0)
#1525000
b10011 [
1)
#1530000
0)
#1535000
b10100 [
1)
#1540000
0)
#1545000
b10101 [
1)
#1550000
0)
#1555000
b10110 [
1)
#1560000
0)
#1565000
b10111 [
1)
#1570000
0)
#1575000
b11000 [
1)
#1580000
0)
#1585000
b11001 [
1)
#1590000
0)
#1595000
b11010 [
1)
#1600000
0)
#1605000
b11011 [
1)
#1610000
0)
#1615000
b11100 [
1)
#1620000
0)
#1625000
b11101 [
1)
#1630000
0)
#1635000
b11110 [
1)
#1640000
0)
#1645000
b11111 [
1)
#1650000
0)
#1655000
b100000 [
1)
#1660000
0)
#1665000
b100001 [
1)
#1670000
0)
#1675000
b100010 [
1)
#1680000
0)
#1685000
b100011 [
1)
#1690000
0)
#1695000
b100100 [
1)
#1700000
0)
#1705000
b100101 [
1)
#1710000
0)
#1715000
b100110 [
1)
#1720000
0)
#1725000
b100111 [
1)
#1730000
0)
#1735000
b101000 [
1)
#1740000
0)
#1745000
b101001 [
1)
#1750000
0)
#1755000
b101010 [
1)
#1760000
0)
#1765000
b101011 [
1)
#1770000
0)
#1775000
b101100 [
1)
