RTL/immediate_generator.v
module immediate_generator (
	input [31:0] instruction,
    output reg [31:0] imm);
	
	wire [6:0] opcode;
	
	assign opcode = instruction[6:0];
	
	always @(*)
	begin
		case(opcode)
			7'b0010011,
			7'b0000011,
			7'b1100111 : imm = {{20{instruction[31]}},instruction[31:20]};
			7'b0100011 : imm = {{20{instruction[31]}},instruction[31:25],instruction[11:7]};
			7'b1100011 : imm = {{19{instruction[31]}},instruction[31],instruction[7],instruction[30:25],instruction[11:8],1'b0};
			7'b0110111,
			7'b0010111 : imm = {instruction[31:12],12'd0};
			7'b1101111 : imm = {{11{instruction[31]}},instruction[31],instruction[19:12],instruction[20],instruction[30:21],1'b0};
			default    : imm = 32'd0; 
		endcase
	end
endmodule

tb/immediate_gen_tb.v
`timescale 1ns/1ps

module immediate_generator_tb;

    reg  [31:0] instruction;
    wire [31:0] imm;
    integer     error_count;
    integer     test_count;

    immediate_generator uut (
        .instruction(instruction),
        .imm(imm)
    );

    // ------------------------------------------------------------
    // Golden reference model -- written independently from the
    // RISC-V spec, NOT copied from the DUT. If you copy the DUT's
    // logic here, any DUT bug gets silently duplicated and this
    // testbench will never catch it.
    // ------------------------------------------------------------
    function [31:0] expected_imm;
        input [31:0] instr;
        reg [6:0] op;
        begin
            op = instr[6:0];
            case(op)
                7'b0010011, 7'b0000011, 7'b1100111:                 // I-type
                    expected_imm = {{20{instr[31]}}, instr[31:20]};
                7'b0100011:                                          // S-type
                    expected_imm = {{20{instr[31]}}, instr[31:25], instr[11:7]};
                7'b1100011:                                          // B-type
                    expected_imm = {{19{instr[31]}}, instr[31], instr[7],
                                     instr[30:25], instr[11:8], 1'b0};
                7'b0110111, 7'b0010111:                               // U-type
                    expected_imm = {instr[31:12], 12'b0};
                7'b1101111:                                           // J-type
                    expected_imm = {{11{instr[31]}}, instr[31], instr[19:12],
                                     instr[20], instr[30:21], 1'b0};
                default:
                    expected_imm = 32'd0;
            endcase
        end
    endfunction

    // ------------------------------------------------------------
    // Checker task -- reports every mismatch, never stops early,
    // so one bug doesn't hide the rest of the report.
    // ------------------------------------------------------------
    task check_imm;
        input [31:0] instr;
        input [30*8:1] test_name;
        reg [31:0] expected;
        begin
            instruction = instr;
            #1;
            expected = expected_imm(instr);
            test_count = test_count + 1;
            if (imm === expected)
                $display("PASS [%0s] instr=%h  imm=%h", test_name, instr, imm);
            else begin
                $display("FAIL [%0s] instr=%h  imm=%h  expected=%h",
                           test_name, instr, imm, expected);
                error_count = error_count + 1;
            end
        end
    endtask

    // ------------------------------------------------------------
    // Directed tests -- built from named fields, not hand-typed hex,
    // so they're self-documenting and can't hide a transcription bug.
    // ------------------------------------------------------------
    task directed_tests;
        begin
            // I-type: positive immediate
            // addi x1, x0, 5
            check_imm({12'd5, 5'd0, 3'b000, 5'd1, 7'b0010011}, "I-type positive (ADDI)");

            // I-type: negative immediate -- tests sign extension
            // addi x1, x0, -1
            check_imm({12'hFFF, 5'd0, 3'b000, 5'd1, 7'b0010011}, "I-type negative (ADDI)");

            // I-type via load opcode
            // lw x2, -4(x3)
            check_imm({12'hFFC, 5'd3, 3'b010, 5'd2, 7'b0000011}, "I-type load (LW, negative)");

            // I-type via jalr opcode
            check_imm({12'd8, 5'd1, 3'b000, 5'd0, 7'b1100111}, "I-type JALR");

            // S-type: immediate split across two fields, positive
            // sw x2, 4(x1)
            check_imm({7'b0000000, 5'd2, 5'd1, 3'b010, 5'd4, 7'b0100011}, "S-type positive (SW)");

            // S-type: negative immediate, split fields + sign extension
            // sw x2, -4(x1)  -> imm = -4 = 12'hFFC -> [11:5]=1111111 [4:0]=11100
            check_imm({7'b1111111, 5'd2, 5'd1, 3'b010, 5'd28, 7'b0100011}, "S-type negative (SW)");

            // B-type: positive offset, must check LSB forced to 0
            // beq x1, x2, +8  -> imm[12:1] encodes 8 -> imm[3]=1, rest 0
            check_imm({1'b0, 6'b000000, 5'd2, 5'd1, 3'b000, 4'b0100, 1'b0, 7'b1100011}, "B-type positive (BEQ)");

            // B-type: negative offset -- tests sign extension AND LSB=0
            check_imm({1'b1, 6'b111111, 5'd2, 5'd1, 3'b000, 4'b1100, 1'b0, 7'b1100011}, "B-type negative (BEQ)");

            // U-type: low 12 bits must always be 0
            // lui x1, 0x12345
            check_imm({20'h12345, 5'd1, 7'b0110111}, "U-type (LUI)");

            // U-type via AUIPC
            check_imm({20'hFFFFF, 5'd1, 7'b0010111}, "U-type (AUIPC, all 1s)");

            // J-type: heavily scrambled bit order, LSB must be 0
            // jal x1, +16
            check_imm({1'b0, 10'b0000001000, 1'b0, 8'b00000000, 5'd1, 7'b1101111}, "J-type positive (JAL)");

            // J-type: negative offset -- sign extension across the scramble
            check_imm({1'b1, 10'b1111111111, 1'b1, 8'b11111111, 5'd1, 7'b1101111}, "J-type negative (JAL)");

            // Unhandled opcode (R-type) -- must hit default, return exactly 0
            check_imm({7'b0000000, 5'd2, 5'd1, 3'b000, 5'd3, 7'b0110011}, "R-type (no immediate, expect 0)");
        end
    endtask

    // ------------------------------------------------------------
    // Randomized tests -- opcode constrained to the 6 valid types
    // so we're not wasting iterations on opcodes that always hit default.
    // ------------------------------------------------------------
    task random_tests;
        integer i;
        reg [6:0] valid_opcodes [0:5];
        reg [31:0] instr;
        begin
            valid_opcodes[0] = 7'b0010011; // I-type (ADDI etc.)
            valid_opcodes[1] = 7'b0000011; // I-type (loads)
            valid_opcodes[2] = 7'b1100111; // I-type (JALR)
            valid_opcodes[3] = 7'b0100011; // S-type
            valid_opcodes[4] = 7'b1100011; // B-type
            valid_opcodes[5] = 7'b1101111; // J-type

            for (i = 0; i < 200; i = i + 1) begin
                instr = $urandom;
                instr[6:0] = valid_opcodes[{$random} % 6];
                check_imm(instr, "random");
            end

            // also fuzz a few random UNKNOWN opcodes to confirm default=0 holds broadly
            for (i = 0; i < 20; i = i + 1) begin
                instr = $urandom;
                instr[6:0] = 7'b0110011; // R-type, always unhandled -> must be 0
                check_imm(instr, "random R-type (expect 0)");
            end
        end
    endtask

    initial begin
        error_count = 0;
        test_count  = 0;

        directed_tests;
        random_tests;

        $display("--------------------------------------------------");
        $display("TESTS RUN   : %0d", test_count);
        $display("TESTS FAILED: %0d", error_count);
        if (error_count == 0)
            $display("RESULT: ALL TESTS PASSED");
        else
            $display("RESULT: %0d TEST(S) FAILED -- see FAIL lines above", error_count);
        $display("--------------------------------------------------");

        $finish;
    end

    initial begin
        $dumpfile("immediate_generator.vcd");
        $dumpvars(0, immediate_generator_tb);
    end

endmodule

SIM/immediate_generator.vcd
$date
	Sun Jul 19 23:22:06 2026
$end
$version
	Icarus Verilog
$end
$timescale
	1ps
$end
$scope module immediate_generator_tb $end
$var wire 32 ! imm [31:0] $end
$var reg 32 " instruction [31:0] $end
$var integer 32 # error_count [31:0] $end
$var integer 32 $ test_count [31:0] $end
$scope function expected_imm $end
$var reg 32 % instr [31:0] $end
$var reg 7 & op [6:0] $end
$upscope $end
$scope module uut $end
$var wire 32 ' instruction [31:0] $end
$var wire 7 ( opcode [6:0] $end
$var reg 32 ) imm [31:0] $end
$upscope $end
$scope task check_imm $end
$var reg 32 * expected [31:0] $end
$var reg 32 + instr [31:0] $end
$var reg 240 , test_name [240:1] $end
$upscope $end
$scope task directed_tests $end
$upscope $end
$scope task random_tests $end
$var reg 32 - instr [31:0] $end
$var integer 32 . i [31:0] $end
$upscope $end
$upscope $end
$enddefinitions $end
$comment Show the parameter values. $end
$dumpall
$end
#0
$dumpvars
bx .
bx -
b1001001001011010111010001111001011100000110010100100000011100000110111101110011011010010111010001101001011101100110010100100000001010000100000101000100010001000100100100101001 ,
b10100000000000010010011 +
bx *
b101 )
b10011 (
b10100000000000010010011 '
bx &
bx %
b0 $
b0 #
b10100000000000010010011 "
b101 !
$end
#1000
b11111111111111111111111111111111 !
b11111111111111111111111111111111 )
b11111111111100000000000010010011 "
b11111111111100000000000010010011 '
b1001001001011010111010001111001011100000110010100100000011011100110010101100111011000010111010001101001011101100110010100100000001010000100000101000100010001000100100100101001 ,
b11111111111100000000000010010011 +
b1 $
b101 *
b10011 &
b10100000000000010010011 %
#2000
b11111111111111111111111111111100 !
b11111111111111111111111111111100 )
b11 (
b11111111110000011010000100000011 "
b11111111110000011010000100000011 '
b100100100101101011101000111100101110000011001010010000001101100011011110110000101100100001000000010100001001100010101110010110000100000011011100110010101100111011000010111010001101001011101100110010100101001 ,
b11111111110000011010000100000011 +
b10 $
b11111111111111111111111111111111 *
b11111111111100000000000010010011 %
#3000
b1000 !
b1000 )
b1100111 (
b100000001000000001100111 "
b100000001000000001100111 '
b100100100101101011101000111100101110000011001010010000001001010010000010100110001010010 ,
b100000001000000001100111 +
b11 $
b11111111111111111111111111111100 *
b11 &
b11111111110000011010000100000011 %
#4000
b100 !
b100 )
b100011 (
b1000001010001000100011 "
b1000001010001000100011 '
b101001100101101011101000111100101110000011001010010000001110000011011110111001101101001011101000110100101110110011001010010000000101000010100110101011100101001 ,
b1000001010001000100011 +
b100 $
b1000 *
b1100111 &
b100000001000000001100111 %
#5000
b11111111111111111111111111111100 !
b11111111111111111111111111111100 )
b11111110001000001010111000100011 "
b11111110001000001010111000100011 '
b101001100101101011101000111100101110000011001010010000001101110011001010110011101100001011101000110100101110110011001010010000000101000010100110101011100101001 ,
b11111110001000001010111000100011 +
b101 $
b100 *
b100011 &
b1000001010001000100011 %
#6000
b1000 !
b1000 )
b1100011 (
b1000001000010001100011 "
b1000001000010001100011 '
b10000100010110101110100011110010111000001100101001000000111000001101111011100110110100101110100011010010111011001100101001000000010100001000010010001010101000100101001 ,
b1000001000010001100011 +
b110 $
b11111111111111111111111111111100 *
b11111110001000001010111000100011 %
#7000
b11111111111111111111011111111000 !
b11111111111111111111011111111000 )
b11111110001000001000110001100011 "
b11111110001000001000110001100011 '
b10000100010110101110100011110010111000001100101001000000110111001100101011001110110000101110100011010010111011001100101001000000010100001000010010001010101000100101001 ,
b11111110001000001000110001100011 +
b111 $
b1000 *
b1100011 &
b1000001000010001100011 %
#8000
b10010001101000101000000000000 !
b10010001101000101000000000000 )
b110111 (
b10010001101000101000010110111 "
b10010001101000101000010110111 '
b10101010010110101110100011110010111000001100101001000000010100001001100010101010100100100101001 ,
b10010001101000101000010110111 +
b1000 $
b11111111111111111111011111111000 *
b11111110001000001000110001100011 %
#9000
b11111111111111111111000000000000 !
b11111111111111111111000000000000 )
b10111 (
b11111111111111111111000010010111 "
b11111111111111111111000010010111 '
b1010101001011010111010001111001011100000110010100100000001010000100000101010101010010010101000001000011001011000010000001100001011011000110110000100000001100010111001100101001 ,
b11111111111111111111000010010111 +
b1001 $
b10010001101000101000000000000 *
b110111 &
b10010001101000101000010110111 %
#10000
b10000 !
b10000 )
b1101111 (
b1000000000000000011101111 "
b1000000000000000011101111 '
b10010100010110101110100011110010111000001100101001000000111000001101111011100110110100101110100011010010111011001100101001000000010100001001010010000010100110000101001 ,
b1000000000000000011101111 +
b1010 $
b11111111111111111111000000000000 *
b10111 &
b11111111111111111111000010010111 %
#11000
b11111111111111111111111111111110 !
b11111111111111111111111111111110 )
b11111111111111111111000011101111 "
b11111111111111111111000011101111 '
b10010100010110101110100011110010111000001100101001000000110111001100101011001110110000101110100011010010111011001100101001000000010100001001010010000010100110000101001 ,
b11111111111111111111000011101111 +
b1011 $
b10000 *
b1101111 &
b1000000000000000011101111 %
#12000
b0 !
b0 )
b110011 (
b1000001000000110110011 "
b1000001000000110110011 '
b1011010111010001111001011100000110010100100000001010000110111001101111001000000110100101101101011011010110010101100100011010010110000101110100011001010010110000100000011001010111100001110000011001010110001101110100001000000011000000101001 ,
b1000001000000110110011 +
b1100 $
b11111111111111111111111111111110 *
b11111111111111111111000011101111 %
#13000
b11111111111111111111100100100001 !
b11111111111111111111100100100001 )
b1100111 (
b10010010000101010011010101100111 "
b10010010000101010011010101100111 '
b11100100110000101101110011001000110111101101101 ,
b10010010000101010011010101100111 +
b10010010000101010011010101100111 -
b0 .
b1101 $
b0 *
b110011 &
b1000001000000110110011 %
#14000
b10000011101 !
b10000011101 )
b100011 (
b1000000100010010101111010100011 "
b1000000100010010101111010100011 '
b1000000100010010101111010100011 +
b1000000100010010101111010100011 -
b1 .
b1110 $
b11111111111111111111100100100001 *
b1100111 &
b10010010000101010011010101100111 %
#15000
b1001000 !
b1001000 )
b11 (
b100100001001101011000000011 "
b100100001001101011000000011 '
b100100001001101011000000011 +
b100100001001101011000000011 -
b10 .
b1111 $
b10000011101 *
b100011 &
b1000000100010010101111010100011 %
#16000
b101101100011110 !
b101101100011110 )
b1101111 (
b110001111100000101011001101111 "
b110001111100000101011001101111 '
b110001111100000101011001101111 +
b110001111100000101011001101111 -
b11 .
b10000 $
b1001000 *
b11 &
b100100001001101011000000011 %
#17000
b11111111111111111111100001110110 !
b11111111111111111111100001110110 )
b100011 (
b10000110101110010111101100100011 "
b10000110101110010111101100100011 '
b10000110101110010111101100100011 +
b10000110101110010111101100100011 -
b100 .
b10001 $
b101101100011110 *
b1101111 &
b110001111100000101011001101111 %
#18000
b11111111111111111001110001101100 !
b11111111111111111001110001101100 )
b1101111 (
b11000110110111111001100111101111 "
b11000110110111111001100111101111 '
b11000110110111111001100111101111 +
b11000110110111111001100111101111 -
b101 .
b10010 $
b11111111111111111111100001110110 *
b100011 &
b10000110101110010111101100100011 %
#19000
b101000001100101100 !
b101000001100101100 )
b110010110000101000010001101111 "
b110010110000101000010001101111 '
b110010110000101000010001101111 +
b110010110000101000010001101111 -
b110 .
b10011 $
b11111111111111111001110001101100 *
b1101111 &
b11000110110111111001100111101111 %
#20000
b10000100 !
b10000100 )
b1100011 (
b1001001101110101001001100011 "
b1001001101110101001001100011 '
b1001001101110101001001100011 +
b1001001101110101001001100011 -
b111 .
b10100 $
b101000001100101100 *
b110010110000101000010001101111 %
#21000
b11111111111111111111100000000110 !
b11111111111111111111100000000110 )
b100011 (
b10000000111100111110001100100011 "
b10000000111100111110001100100011 '
b10000000111100111110001100100011 +
b10000000111100111110001100100011 -
b1000 .
b10101 $
b10000100 *
b1100011 &
b1001001101110101001001100011 %
#22000
b11111111111111111111100001101101 !
b11111111111111111111100001101101 )
b11 (
b10000110110101111100110100000011 "
b10000110110101111100110100000011 '
b10000110110101111100110100000011 +
b10000110110101111100110100000011 -
b1001 .
b10110 $
b11111111111111111111100000000110 *
b100011 &
b10000000111100111110001100100011 %
#23000
b11111111111111111111101110110010 !
b11111111111111111111101110110010 )
b10011 (
b10111011001000111111000100010011 "
b10111011001000111111000100010011 '
b10111011001000111111000100010011 +
b10111011001000111111000100010011 -
b1010 .
b10111 $
b11111111111111111111100001101101 *
b11 &
b10000110110101111100110100000011 %
#24000
b11111111111111011100000111101000 !
b11111111111111011100000111101000 )
b1101111 (
b10011110100011011100110101101111 "
b10011110100011011100110101101111 '
b10011110100011011100110101101111 +
b10011110100011011100110101101111 -
b1011 .
b11000 $
b11111111111111111111101110110010 *
b10011 &
b10111011001000111111000100010011 %
#25000
b11111111111111111111111101101111 !
b11111111111111111111111101101111 )
b100011 (
b11110110110101000101011110100011 "
b11110110110101000101011110100011 '
b11110110110101000101011110100011 +
b11110110110101000101011110100011 -
b1100 .
b11001 $
b11111111111111011100000111101000 *
b1101111 &
b10011110100011011100110101101111 %
#26000
b11111111111111111111110001101110 !
b11111111111111111111110001101110 )
b1100011 (
b11000110001011011111011111100011 "
b11000110001011011111011111100011 '
b11000110001011011111011111100011 +
b11000110001011011111011111100011 -
b1101 .
b11010 $
b11111111111111111111111101101111 *
b100011 &
b11110110110101000101011110100011 %
#27000
b11111111111111111111111111001111 !
b11111111111111111111111111001111 )
b11 (
b11111100111111011110100110000011 "
b11111100111111011110100110000011 '
b11111100111111011110100110000011 +
b11111100111111011110100110000011 -
b1110 .
b11011 $
b11111111111111111111110001101110 *
b1100011 &
b11000110001011011111011111100011 %
#28000
b11000110011 !
b11000110011 )
b10011 (
b1100011001101110010010010010011 "
b1100011001101110010010010010011 '
b1100011001101110010010010010011 +
b1100011001101110010010010010011 -
b1111 .
b11100 $
b11111111111111111111111111001111 *
b11 &
b11111100111111011110100110000011 %
#29000
b11000101111 !
b11000101111 )
b11 (
b1100010111101111000010010000011 "
b1100010111101111000010010000011 '
b1100010111101111000010010000011 +
b1100010111101111000010010000011 -
b10000 .
b11101 $
b11000110011 *
b10011 &
b1100011001101110010010010010011 %
#30000
b10101010001 !
b10101010001 )
b10011 (
b1010101000100111101001010010011 "
b1010101000100111101001010010011 '
b1010101000100111101001010010011 +
b1010101000100111101001010010011 -
b10001 .
b11110 $
b11000101111 *
b11 &
b1100010111101111000010010000011 %
#31000
b11111111111111111111111100101111 !
b11111111111111111111111100101111 )
b100011 (
b11110010101011111111011110100011 "
b11110010101011111111011110100011 '
b11110010101011111111011110100011 +
b11110010101011111111011110100011 -
b10010 .
b11111 $
b10101010001 *
b10011 &
b1010101000100111101001010010011 %
#32000
b1110100100 !
b1110100100 )
b111011110100100111001000100011 "
b111011110100100111001000100011 '
b111011110100100111001000100011 +
b111011110100100111001000100011 -
b10011 .
b100000 $
b11111111111111111111111100101111 *
b100011 &
b11110010101011111111011110100011 %
#33000
b10010011 !
b10010011 )
b1100111 (
b1001001100101101011001100111 "
b1001001100101101011001100111 '
b1001001100101101011001100111 +
b1001001100101101011001100111 -
b10100 .
b100001 $
b1110100100 *
b111011110100100111001000100011 %
#34000
b11111111111111111111110001110111 !
b11111111111111111111110001110111 )
b100011 (
b11000111111011001101101110100011 "
b11000111111011001101101110100011 '
b11000111111011001101101110100011 +
b11000111111011001101101110100011 -
b10101 .
b100010 $
b10010011 *
b1100111 &
b1001001100101101011001100111 %
#35000
b11111111111111111111111110010011 !
b11111111111111111111111110010011 )
b10011 (
b11111001001100000110100110010011 "
b11111001001100000110100110010011 '
b11111001001100000110100110010011 +
b11111001001100000110100110010011 -
b10110 .
b100011 $
b11111111111111111111110001110111 *
b100011 &
b11000111111011001101101110100011 %
#36000
b11001110111 !
b11001110111 )
b1100111011101101001011010010011 "
b1100111011101101001011010010011 '
b1100111011101101001011010010011 +
b1100111011101101001011010010011 -
b10111 .
b100100 $
b11111111111111111111111110010011 *
b10011 &
b11111001001100000110100110010011 %
#37000
b111101010100 !
b111101010100 )
b1100011 (
b1110100000000000111101011100011 "
b1110100000000000111101011100011 '
b1110100000000000111101011100011 +
b1110100000000000111101011100011 -
b11000 .
b100101 $
b11001110111 *
b1100111011101101001011010010011 %
#38000
b11000101100 !
b11000101100 )
b11 (
b1100010110010100100111010000011 "
b1100010110010100100111010000011 '
b1100010110010100100111010000011 +
b1100010110010100100111010000011 -
b11001 .
b100110 $
b111101010100 *
b1100011 &
b1110100000000000111101011100011 %
#39000
b11111111111111111111101011100101 !
b11111111111111111111101011100101 )
b1100111 (
b10101110010110000100100101100111 "
b10101110010110000100100101100111 '
b10101110010110000100100101100111 +
b10101110010110000100100101100111 -
b11010 .
b100111 $
b11000101100 *
b11 &
b1100010110010100100111010000011 %
#40000
b11100010010111101000 !
b11100010010111101000 )
b1101111 (
b1011110100011100010100011101111 "
b1011110100011100010100011101111 '
b1011110100011100010100011101111 +
b1011110100011100010100011101111 -
b11011 .
b101000 $
b11111111111111111111101011100101 *
b1100111 &
b10101110010110000100100101100111 %
#41000
b101101010 !
b101101010 )
b11 (
b10110101010110101100000000011 "
b10110101010110101100000000011 '
b10110101010110101100000000011 +
b10110101010110101100000000011 -
b11100 .
b101001 $
b11100010010111101000 *
b1101111 &
b1011110100011100010100011101111 %
#42000
b1100101010 !
b1100101010 )
b110010101001110010011000000011 "
b110010101001110010011000000011 '
b110010101001110010011000000011 +
b110010101001110010011000000011 -
b11101 .
b101010 $
b101101010 *
b11 &
b10110101010110101100000000011 %
#43000
b1100011110 !
b1100011110 )
b110001111011110110001000000011 "
b110001111011110110001000000011 '
b110001111011110110001000000011 +
b110001111011110110001000000011 -
b11110 .
b101011 $
b1100101010 *
b110010101001110010011000000011 %
#44000
b11111111111111111111000001001110 !
b11111111111111111111000001001110 )
b1100011 (
b10000101011100111000011101100011 "
b10000101011100111000011101100011 '
b10000101011100111000011101100011 +
b10000101011100111000011101100011 -
b11111 .
b101100 $
b1100011110 *
b110001111011110110001000000011 %
#45000
b10000000011 !
b10000000011 )
b1100111 (
b1000000001110110010001011100111 "
b1000000001110110010001011100111 '
b1000000001110110010001011100111 +
b1000000001110110010001011100111 -
b100000 .
b101101 $
b11111111111111111111000001001110 *
b1100011 &
b10000101011100111000011101100011 %
#46000
b11111111111111111111000100000010 !
b11111111111111111111000100000010 )
b1100011 (
b10010000011001000010000101100011 "
b10010000011001000010000101100011 '
b10010000011001000010000101100011 +
b10010000011001000010000101100011 -
b100001 .
b101110 $
b10000000011 *
b1100111 &
b1000000001110110010001011100111 %
#47000
b11111111111111111111110101010111 !
b11111111111111111111110101010111 )
b10011 (
b11010101011110000100010110010011 "
b11010101011110000100010110010011 '
b11010101011110000100010110010011 +
b11010101011110000100010110010011 -
b100010 .
b101111 $
b11111111111111111111000100000010 *
b1100011 &
b10010000011001000010000101100011 %
#48000
b10011111001 !
b10011111001 )
b100011 (
b1001110110011001100110010100011 "
b1001110110011001100110010100011 '
b1001110110011001100110010100011 +
b1001110110011001100110010100011 -
b100011 .
b110000 $
b11111111111111111111110101010111 *
b10011 &
b11010101011110000100010110010011 %
#49000
b10010110010 !
b10010110010 )
b10011 (
b1001011001000000011111010010011 "
b1001011001000000011111010010011 '
b1001011001000000011111010010011 +
b1001011001000000011111010010011 -
b100100 .
b110001 $
b10011111001 *
b100011 &
b1001110110011001100110010100011 %
#50000
b10010000 !
b10010000 )
b100011 (
b1001100000111011100000100011 "
b1001100000111011100000100011 '
b1001100000111011100000100011 +
b1001100000111011100000100011 -
b100101 .
b110010 $
b10010110010 *
b10011 &
b1001011001000000011111010010011 %
#51000
b1101011 !
b1101011 )
b11 (
b110101111000011100000000011 "
b110101111000011100000000011 '
b110101111000011100000000011 +
b110101111000011100000000011 -
b100110 .
b110011 $
b10010000 *
b100011 &
b1001100000111011100000100011 %
#52000
b1010001100 !
b1010001100 )
b100011 (
b101001101001111101011000100011 "
b101001101001111101011000100011 '
b101001101001111101011000100011 +
b101001101001111101011000100011 -
b100111 .
b110100 $
b1101011 *
b11 &
b110101111000011100000000011 %
#53000
b11111111111111111111101101011010 !
b11111111111111111111101101011010 )
b10110101100111111101110100100011 "
b10110101100111111101110100100011 '
b10110101100111111101110100100011 +
b10110101100111111101110100100011 -
b101000 .
b110101 $
b1010001100 *
b100011 &
b101001101001111101011000100011 %
#54000
b11010101010 !
b11010101010 )
b11 (
b1101010101001100010101010000011 "
b1101010101001100010101010000011 '
b1101010101001100010101010000011 +
b1101010101001100010101010000011 -
b101001 .
b110110 $
b11111111111111111111101101011010 *
b10110101100111111101110100100011 %
#55000
b10001 !
b10001 )
b10011 (
b1000101110100101000010011 "
b1000101110100101000010011 '
b1000101110100101000010011 +
b1000101110100101000010011 -
b101010 .
b110111 $
b11010101010 *
b11 &
b1101010101001100010101010000011 %
#56000
b10101110101 !
b10101110101 )
b1010111010101100011111010010011 "
b1010111010101100011111010010011 '
b1010111010101100011111010010011 +
b1010111010101100011111010010011 -
b101011 .
b111000 $
b10001 *
b10011 &
b1000101110100101000010011 %
#57000
b11111111111111111111100011110010 !
b11111111111111111111100011110010 )
b100011 (
b10001110111111111110100100100011 "
b10001110111111111110100100100011 '
b10001110111111111110100100100011 +
b10001110111111111110100100100011 -
b101100 .
b111001 $
b10101110101 *
b1010111010101100011111010010011 %
#58000
b1010111011001111100 !
b1010111011001111100 )
b1101111 (
b1100111110001010111001011101111 "
b1100111110001010111001011101111 '
b1100111110001010111001011101111 +
b1100111110001010111001011101111 -
b101101 .
b111010 $
b11111111111111111111100011110010 *
b100011 &
b10001110111111111110100100100011 %
#59000
b11111111111101000100000100011000 !
b11111111111101000100000100011000 )
b10010001100001000100100101101111 "
b10010001100001000100100101101111 '
b10010001100001000100100101101111 +
b10010001100001000100100101101111 -
b101110 .
b111011 $
b1010111011001111100 *
b1101111 &
b1100111110001010111001011101111 %
#60000
b11111111111111111111100001010000 !
b11111111111111111111100001010000 )
b1100111 (
b10000101000010010110010101100111 "
b10000101000010010110010101100111 '
b10000101000010010110010101100111 +
b10000101000010010110010101100111 -
b101111 .
b111100 $
b11111111111101000100000100011000 *
b10010001100001000100100101101111 %
#61000
b111001010100 !
b111001010100 )
b1100011 (
b1100101011100110000101011100011 "
b1100101011100110000101011100011 '
b1100101011100110000101011100011 +
b1100101011100110000101011100011 -
b110000 .
b111101 $
b11111111111111111111100001010000 *
b1100111 &
b10000101000010010110010101100111 %
#62000
b111111000 !
b111111000 )
b11110001100010100110001100011 "
b11110001100010100110001100011 '
b11110001100010100110001100011 +
b11110001100010100110001100011 -
b110001 .
b111110 $
b111001010100 *
b1100011 &
b1100101011100110000101011100011 %
#63000
b11111111111111111111111110010110 !
b11111111111111111111111110010110 )
b1100111 (
b11111001011010001011110111100111 "
b11111001011010001011110111100111 '
b11111001011010001011110111100111 +
b11111001011010001011110111100111 -
b110010 .
b111111 $
b111111000 *
b11110001100010100110001100011 %
#64000
b11111111111111111111110001010010 !
b11111111111111111111110001010010 )
b11000101001011100110000111100111 "
b11000101001011100110000111100111 '
b11000101001011100110000111100111 +
b11000101001011100110000111100111 -
b110011 .
b1000000 $
b11111111111111111111111110010110 *
b1100111 &
b11111001011010001011110111100111 %
#65000
b11111111111111111111101000001100 !
b11111111111111111111101000001100 )
b11 (
b10100000110001001011001100000011 "
b10100000110001001011001100000011 '
b10100000110001001011001100000011 +
b10100000110001001011001100000011 -
b110100 .
b1000001 $
b11111111111111111111110001010010 *
b11000101001011100110000111100111 %
#66000
b11011000100 !
b11011000100 )
b10011 (
b1101100010010110011010010010011 "
b1101100010010110011010010010011 '
b1101100010010110011010010010011 +
b1101100010010110011010010010011 -
b110101 .
b1000010 $
b11111111111111111111101000001100 *
b11 &
b10100000110001001011001100000011 %
#67000
b11111111111111111111101111000010 !
b11111111111111111111101111000010 )
b1100111 (
b10111100001000001111001101100111 "
b10111100001000001111001101100111 '
b10111100001000001111001101100111 +
b10111100001000001111001101100111 -
b110110 .
b1000011 $
b11011000100 *
b10011 &
b1101100010010110011010010010011 %
#68000
b10001000101 !
b10001000101 )
b100011 (
b1000100100010100001001010100011 "
b1000100100010100001001010100011 '
b1000100100010100001001010100011 +
b1000100100010100001001010100011 -
b110111 .
b1000100 $
b11111111111111111111101111000010 *
b1100111 &
b10111100001000001111001101100111 %
#69000
b11111111111111111111111101011100 !
b11111111111111111111111101011100 )
b11 (
b11110101110001010000110110000011 "
b11110101110001010000110110000011 '
b11110101110001010000110110000011 +
b11110101110001010000110110000011 -
b111000 .
b1000101 $
b10001000101 *
b100011 &
b1000100100010100001001010100011 %
#70000
b11111111111111111111110110101010 !
b11111111111111111111110110101010 )
b1100011 (
b11011011000000100110010111100011 "
b11011011000000100110010111100011 '
b11011011000000100110010111100011 +
b11011011000000100110010111100011 -
b111001 .
b1000110 $
b11111111111111111111111101011100 *
b11 &
b11110101110001010000110110000011 %
#71000
b11111111111111111111111000110100 !
b11111111111111111111111000110100 )
b10011 (
b11100011010010111111100110010011 "
b11100011010010111111100110010011 '
b11100011010010111111100110010011 +
b11100011010010111111100110010011 -
b111010 .
b1000111 $
b11111111111111111111110110101010 *
b1100011 &
b11011011000000100110010111100011 %
#72000
b11111111111111111111110101100110 !
b11111111111111111111110101100110 )
b1100011 (
b11010111000101010001001111100011 "
b11010111000101010001001111100011 '
b11010111000101010001001111100011 +
b11010111000101010001001111100011 -
b111011 .
b1001000 $
b11111111111111111111111000110100 *
b10011 &
b11100011010010111111100110010011 %
#73000
b110111100100 !
b110111100100 )
b1011110011101010000001011100011 "
b1011110011101010000001011100011 '
b1011110011101010000001011100011 +
b1011110011101010000001011100011 -
b111100 .
b1001001 $
b11111111111111111111110101100110 *
b1100011 &
b11010111000101010001001111100011 %
#74000
b11111111111111111111100101010000 !
b11111111111111111111100101010000 )
b1100111 (
b10010101000011111101110101100111 "
b10010101000011111101110101100111 '
b10010101000011111101110101100111 +
b10010101000011111101110101100111 -
b111101 .
b1001010 $
b110111100100 *
b1011110011101010000001011100011 %
#75000
b1010100 !
b1010100 )
b100011 (
b101110101111001101000100011 "
b101110101111001101000100011 '
b101110101111001101000100011 +
b101110101111001101000100011 -
b111110 .
b1001011 $
b11111111111111111111100101010000 *
b1100111 &
b10010101000011111101110101100111 %
#76000
b1111011101110001000 !
b1111011101110001000 )
b1101111 (
b111000100101111011111001101111 "
b111000100101111011111001101111 '
b111000100101111011111001101111 +
b111000100101111011111001101111 -
b111111 .
b1001100 $
b1010100 *
b100011 &
b101110101111001101000100011 %
#77000
b11111111111100100100110000101110 !
b11111111111100100100110000101110 )
b11000010111100100100000111101111 "
b11000010111100100100000111101111 '
b11000010111100100100000111101111 +
b11000010111100100100000111101111 -
b1000000 .
b1001101 $
b1111011101110001000 *
b1101111 &
b111000100101111011111001101111 %
#78000
b11111111111111111111101001111111 !
b11111111111111111111101001111111 )
b11 (
b10100111111100100101010100000011 "
b10100111111100100101010100000011 '
b10100111111100100101010100000011 +
b10100111111100100101010100000011 -
b1000001 .
b1001110 $
b11111111111100100100110000101110 *
b11000010111100100100000111101111 %
#79000
b111000000 !
b111000000 )
b100011 (
b11101110011000110000000100011 "
b11101110011000110000000100011 '
b11101110011000110000000100011 +
b11101110011000110000000100011 -
b1000010 .
b1001111 $
b11111111111111111111101001111111 *
b11 &
b10100111111100100101010100000011 %
