RTL/register_file.v
module register_file (
	input clk,rst,
	input [4:0] Read_register_1,Read_register_2,
	input [4:0] write_register,
	input [31:0] write_data,
	input reg_write,
	output [31:0] read_data_1 ,read_data_2 );
	
	reg [31:0] memory [0:31];
	integer i;
	
	always @(posedge clk or negedge rst)
	begin
		if(!rst)
			for(i=0;i<32;i=i+1)	
				memory [i] <= 0;
		
		else if (reg_write && write_register != 5'd0)
			memory[write_register] <= write_data;
	end
	
		assign read_data_1 = memory[Read_register_1];
		assign read_data_2 = memory[Read_register_2];

endmodule

tb/register_file_tb1.v
`timescale 1ns/1ps

module register_file_tb;
    reg clk, rst;
    reg [4:0]  Read_register_1, Read_register_2, write_register;
    reg [31:0] write_data;
    reg        reg_write;
    wire [31:0] read_data_1, read_data_2;

    integer test_count;
    integer error_count;

    // ------------------------------------------------------------
    // Scoreboard / shadow model -- an independent prediction of what
    // each register SHOULD hold, maintained entirely in the testbench.
    // We check the DUT's outputs against THIS, never against
    // uut.memory directly -- that keeps the DUT a black box and means
    // the check is validating externally observable behavior, not
    // "does internal signal X match internal signal Y" (which proves
    // nothing about correctness if both were built the same wrong way).
    // ------------------------------------------------------------
    reg [31:0] expected_reg [0:31];

    register_file uut (
        .clk(clk),
        .rst(rst),
        .Read_register_1(Read_register_1),
        .Read_register_2(Read_register_2),
        .write_register(write_register),
        .write_data(write_data),
        .reg_write(reg_write),
        .read_data_1(read_data_1),
        .read_data_2(read_data_2)
    );

    initial begin
        clk = 0;
        forever #5 clk = ~clk;
    end

    // ------------------------------------------------------------
    // Reset: drive it, then verify ALL 32 registers read back zero
    // through the actual read ports (black-box), updating the
    // shadow model to match.
    // ------------------------------------------------------------
    task do_reset;
        integer i;
        begin
            @(negedge clk) rst = 0;
            @(negedge clk) rst = 1;
            @(posedge clk) #1;

            for (i = 0; i < 32; i = i + 1)
                expected_reg[i] = 32'd0;

            for (i = 0; i < 32; i = i + 1) begin
                @(negedge clk)
                Read_register_1 = i;
                Read_register_2 = i;
                #1;
                test_count = test_count + 1;
                if (read_data_1 === 32'd0)
                    $display("PASS [reset] x%0d == 0", i);
                else begin
                    $display("FAIL [reset] x%0d == %h, expected 0", i, read_data_1);
                    error_count = error_count + 1;
                end
            end
        end
    endtask

    // ------------------------------------------------------------
    // Single reusable write task. Handles x0 automatically because
    // the shadow model applies the same hardwired-zero rule the DUT
    // is supposed to implement -- written independently here, not
    // copied from the DUT's if-condition.
    // ------------------------------------------------------------
    task do_write(input [4:0] addr, input [31:0] data);
        begin
            @(negedge clk)
            write_register = addr;
            write_data     = data;
            reg_write      = 1'b1;
            @(posedge clk)
            #1;
            reg_write = 1'b0;

            if (addr != 5'd0)
                expected_reg[addr] = data;
            // addr == 0 -> expected_reg[0] stays 0, matching x0's
            // hardwired-zero behavior -- no DUT internals consulted.

            $display("WRITE x%0d <= %h", addr, data);
        end
    endtask

    // ------------------------------------------------------------
    // Single reusable read+check task. Compares DUT output ports
    // against the shadow model -- this is the actual self-check.
    // ------------------------------------------------------------
    task do_read_check(input [4:0] addr1, input [4:0] addr2);
        begin
            @(negedge clk)
            Read_register_1 = addr1;
            Read_register_2 = addr2;
            #1;
            test_count = test_count + 1;

            if ((read_data_1 === expected_reg[addr1]) &&
                (read_data_2 === expected_reg[addr2]))
            begin
                $display("PASS [read] x%0d=%h  x%0d=%h",
                           addr1, read_data_1, addr2, read_data_2);
            end
            else begin
                $display("FAIL [read] x%0d: got=%h expected=%h | x%0d: got=%h expected=%h",
                           addr1, read_data_1, expected_reg[addr1],
                           addr2, read_data_2, expected_reg[addr2]);
                error_count = error_count + 1;
            end
        end
    endtask

    // ------------------------------------------------------------
    // Directed edge cases -- deterministic, run every single time,
    // targeting the specific corners a register file design tends
    // to get wrong.
    // ------------------------------------------------------------
    task directed_tests;
        begin
            // x0 must reject writes and always read as zero
            do_write(5'd0, 32'hDEADBEEF);
            do_read_check(5'd0, 5'd0);

            // x31 -- the other boundary register, easy to off-by-one
            do_write(5'd31, 32'hCAFEF00D);
            do_read_check(5'd31, 5'd31);

            // ordinary mid-range register
            do_write(5'd15, 32'h12345678);
            do_read_check(5'd15, 5'd0);

            // overwrite: second write to the same register must win
            do_write(5'd5, 32'h11111111);
            do_write(5'd5, 32'h22222222);
            do_read_check(5'd5, 5'd5);

            // both read ports pointed at the SAME register simultaneously
            do_write(5'd7, 32'hA5A5A5A5);
            do_read_check(5'd7, 5'd7);

            // reg_write deasserted -- a write attempt with reg_write=0
            // must NOT change the register
            @(negedge clk)
            write_register = 5'd10;
            write_data     = 32'hFFFFFFFF;
            reg_write      = 1'b0;
            @(posedge clk)
            #1;
            do_read_check(5'd10, 5'd10);   // expected_reg[10] still 0 -- untouched
        end
    endtask

    // ------------------------------------------------------------
    // Randomized regression -- broad coverage on top of the
    // directed corners above.
    // ------------------------------------------------------------
  task random_tests;
    integer i;
    reg [4:0] addr, prev_addr;
    reg [31:0] data;
    begin
        prev_addr = 5'd0;
        for (i = 0; i < 50; i = i + 1) begin
            addr = {$random} % 32;
            data = $urandom;
            do_write(addr, data);

            // rs1: verify the write that just happened
            // rs2: re-check the PREVIOUS write is still intact --
            //      a much stronger retention/isolation check than pure random
            do_read_check(addr, prev_addr);
            prev_addr = addr;
        end
    end
endtask

    initial begin
        test_count  = 0;
        error_count = 0;

        do_reset;
        directed_tests;
        random_tests;

        $display("--------------------------------------------------");
        $display("TESTS RUN   : %0d", test_count);
        $display("TESTS FAILED: %0d", error_count);
        if (error_count == 0)
            $display("RESULT: ALL TESTS PASSED");
        else
            $display("RESULT: %0d TEST(S) FAILED -- see FAIL lines above", error_count);
        $display("--------------------------------------------------");

        $finish;
    end

    initial begin
        $dumpfile("register_file.vcd");
        $dumpvars(0, register_file_tb);
    end

endmodule

SIM/register_file.vcd
$date
	Sun Jul 19 19:17:40 2026
$end
$version
	Icarus Verilog
$end
$timescale
	1ps
$end
$scope module register_file_tb $end
$var wire 32 ! read_data_2 [31:0] $end
$var wire 32 " read_data_1 [31:0] $end
$var reg 5 # Read_register_1 [4:0] $end
$var reg 5 $ Read_register_2 [4:0] $end
$var reg 1 % clk $end
$var reg 1 & reg_write $end
$var reg 1 ' rst $end
$var reg 32 ( write_data [31:0] $end
$var reg 5 ) write_register [4:0] $end
$var integer 32 * error_count [31:0] $end
$var integer 32 + test_count [31:0] $end
$scope module uut $end
$var wire 5 , Read_register_1 [4:0] $end
$var wire 5 - Read_register_2 [4:0] $end
$var wire 1 % clk $end
$var wire 32 . read_data_1 [31:0] $end
$var wire 32 / read_data_2 [31:0] $end
$var wire 1 & reg_write $end
$var wire 1 ' rst $end
$var wire 32 0 write_data [31:0] $end
$var wire 5 1 write_register [4:0] $end
$var integer 32 2 i [31:0] $end
$upscope $end
$scope task directed_tests $end
$upscope $end
$scope task do_read_check $end
$var reg 5 3 addr1 [4:0] $end
$var reg 5 4 addr2 [4:0] $end
$upscope $end
$scope task do_reset $end
$var integer 32 5 i [31:0] $end
$upscope $end
$scope task do_write $end
$var reg 5 6 addr [4:0] $end
$var reg 32 7 data [31:0] $end
$upscope $end
$scope task random_tests $end
$var reg 5 8 addr [4:0] $end
$var reg 32 9 data [31:0] $end
$var reg 5 : prev_addr [4:0] $end
$var integer 32 ; i [31:0] $end
$upscope $end
$upscope $end
$enddefinitions $end
$comment Show the parameter values. $end
$dumpall
$end
#0
$dumpvars
bx ;
bx :
bx 9
bx 8
bx 7
bx 6
bx 5
bx 4
bx 3
bx 2
bx 1
bx 0
bx /
bx .
bx -
bx ,
b0 +
b0 *
bx )
bx (
x'
x&
0%
bx $
bx #
bx "
bx !
$end
#5000
1%
#10000
b100000 2
0'
0%
#15000
b100000 2
1%
#20000
1'
0%
#25000
1%
#26000
b0 5
#30000
b0 !
b0 /
b0 $
b0 -
b0 "
b0 .
b0 #
b0 ,
0%
#31000
b1 5
b1 +
#35000
1%
#40000
b1 $
b1 -
b1 #
b1 ,
0%
#41000
b10 5
b10 +
#45000
1%
#50000
b10 $
b10 -
b10 #
b10 ,
0%
#51000
b11 5
b11 +
#55000
1%
#60000
b11 $
b11 -
b11 #
b11 ,
0%
#61000
b100 5
b100 +
#65000
1%
#70000
b100 $
b100 -
b100 #
b100 ,
0%
#71000
b101 5
b101 +
#75000
1%
#80000
b101 $
b101 -
b101 #
b101 ,
0%
#81000
b110 5
b110 +
#85000
1%
#90000
b110 $
b110 -
b110 #
b110 ,
0%
#91000
b111 5
b111 +
#95000
1%
#100000
b111 $
b111 -
b111 #
b111 ,
0%
#101000
b1000 5
b1000 +
#105000
1%
#110000
b1000 $
b1000 -
b1000 #
b1000 ,
0%
#111000
b1001 5
b1001 +
#115000
1%
#120000
b1001 $
b1001 -
b1001 #
b1001 ,
0%
#121000
b1010 5
b1010 +
#125000
1%
#130000
b1010 $
b1010 -
b1010 #
b1010 ,
0%
#131000
b1011 5
b1011 +
#135000
1%
#140000
b1011 $
b1011 -
b1011 #
b1011 ,
0%
#141000
b1100 5
b1100 +
#145000
1%
#150000
b1100 $
b1100 -
b1100 #
b1100 ,
0%
#151000
b1101 5
b1101 +
#155000
1%
#160000
b1101 $
b1101 -
b1101 #
b1101 ,
0%
#161000
b1110 5
b1110 +
#165000
1%
#170000
b1110 $
b1110 -
b1110 #
b1110 ,
0%
#171000
b1111 5
b1111 +
#175000
1%
#180000
b1111 $
b1111 -
b1111 #
b1111 ,
0%
#181000
b10000 5
b10000 +
#185000
1%
#190000
b10000 $
b10000 -
b10000 #
b10000 ,
0%
#191000
b10001 5
b10001 +
#195000
1%
#200000
b10001 $
b10001 -
b10001 #
b10001 ,
0%
#201000
b10010 5
b10010 +
#205000
1%
#210000
b10010 $
b10010 -
b10010 #
b10010 ,
0%
#211000
b10011 5
b10011 +
#215000
1%
#220000
b10011 $
b10011 -
b10011 #
b10011 ,
0%
#221000
b10100 5
b10100 +
#225000
1%
#230000
b10100 $
b10100 -
b10100 #
b10100 ,
0%
#231000
b10101 5
b10101 +
#235000
1%
#240000
b10101 $
b10101 -
b10101 #
b10101 ,
0%
#241000
b10110 5
b10110 +
#245000
1%
#250000
b10110 $
b10110 -
b10110 #
b10110 ,
0%
#251000
b10111 5
b10111 +
#255000
1%
#260000
b10111 $
b10111 -
b10111 #
b10111 ,
0%
#261000
b11000 5
b11000 +
#265000
1%
#270000
b11000 $
b11000 -
b11000 #
b11000 ,
0%
#271000
b11001 5
b11001 +
#275000
1%
#280000
b11001 $
b11001 -
b11001 #
b11001 ,
0%
#281000
b11010 5
b11010 +
#285000
1%
#290000
b11010 $
b11010 -
b11010 #
b11010 ,
0%
#291000
b11011 5
b11011 +
#295000
1%
#300000
b11011 $
b11011 -
b11011 #
b11011 ,
0%
#301000
b11100 5
b11100 +
#305000
1%
#310000
b11100 $
b11100 -
b11100 #
b11100 ,
0%
#311000
b11101 5
b11101 +
#315000
1%
#320000
b11101 $
b11101 -
b11101 #
b11101 ,
0%
#321000
b11110 5
b11110 +
#325000
1%
#330000
b11110 $
b11110 -
b11110 #
b11110 ,
0%
#331000
b11111 5
b11111 +
#335000
1%
#340000
b11111 $
b11111 -
b11111 #
b11111 ,
0%
#341000
b11011110101011011011111011101111 7
b0 6
b100000 5
b100000 +
#345000
1%
#350000
1&
b11011110101011011011111011101111 (
b11011110101011011011111011101111 0
b0 )
b0 1
0%
#355000
1%
#356000
b0 4
b0 3
0&
#360000
b0 $
b0 -
b0 #
b0 ,
0%
#361000
b11001010111111101111000000001101 7
b11111 6
b100001 +
#365000
1%
#370000
1&
b11001010111111101111000000001101 (
b11001010111111101111000000001101 0
b11111 )
b11111 1
0%
#375000
1%
#376000
b11111 4
b11111 3
0&
#380000
b11001010111111101111000000001101 !
b11001010111111101111000000001101 /
b11111 $
b11111 -
b11001010111111101111000000001101 "
b11001010111111101111000000001101 .
b11111 #
b11111 ,
0%
#381000
b10010001101000101011001111000 7
b1111 6
b100010 +
#385000
1%
#390000
1&
b10010001101000101011001111000 (
b10010001101000101011001111000 0
b1111 )
b1111 1
0%
#395000
1%
#396000
b0 4
b1111 3
0&
#400000
b0 !
b0 /
b0 $
b0 -
b10010001101000101011001111000 "
b10010001101000101011001111000 .
b1111 #
b1111 ,
0%
#401000
b10001000100010001000100010001 7
b101 6
b100011 +
#405000
1%
#410000
1&
b10001000100010001000100010001 (
b10001000100010001000100010001 0
b101 )
b101 1
0%
#415000
1%
#416000
b100010001000100010001000100010 7
0&
#420000
1&
b100010001000100010001000100010 (
b100010001000100010001000100010 0
0%
#425000
1%
#426000
b101 4
b101 3
0&
#430000
b100010001000100010001000100010 !
b100010001000100010001000100010 /
b101 $
b101 -
b100010001000100010001000100010 "
b100010001000100010001000100010 .
b101 #
b101 ,
0%
#431000
b10100101101001011010010110100101 7
b111 6
b100100 +
#435000
1%
#440000
1&
b10100101101001011010010110100101 (
b10100101101001011010010110100101 0
b111 )
b111 1
0%
#445000
1%
#446000
b111 4
b111 3
0&
#450000
b10100101101001011010010110100101 !
b10100101101001011010010110100101 /
b111 $
b111 -
b10100101101001011010010110100101 "
b10100101101001011010010110100101 .
b111 #
b111 ,
0%
#451000
b100101 +
#455000
1%
#460000
b11111111111111111111111111111111 (
b11111111111111111111111111111111 0
b1010 )
b1010 1
0%
#465000
1%
#466000
b1010 4
b1010 3
#470000
b0 !
b0 /
b1010 $
b1010 -
b0 "
b0 .
b1010 #
b1010 ,
0%
#471000
b10010010000101010011010100100100 7
b100 6
b10010010000101010011010100100100 9
b100 8
b0 ;
b0 :
b100110 +
#475000
1%
#480000
1&
b10010010000101010011010100100100 (
b10010010000101010011010100100100 0
b100 )
b100 1
0%
#485000
1%
#486000
b0 4
b100 3
0&
#490000
b0 $
b0 -
b10010010000101010011010100100100 "
b10010010000101010011010100100100 .
b100 #
b100 ,
0%
#491000
b1000000100010010101111010000001 7
b1 6
b1000000100010010101111010000001 9
b1 8
b1 ;
b100 :
b100111 +
#495000
1%
#500000
1&
b1000000100010010101111010000001 (
b1000000100010010101111010000001 0
b1 )
b1 1
0%
#505000
1%
#506000
b100 4
b1 3
0&
#510000
b10010010000101010011010100100100 !
b10010010000101010011010100100100 /
b100 $
b100 -
b1000000100010010101111010000001 "
b1000000100010010101111010000001 .
b1 #
b1 ,
0%
#511000
b100100001001101011000001001 7
b1001 6
b100100001001101011000001001 9
b1001 8
b10 ;
b1 :
b101000 +
#515000
1%
#520000
1&
b100100001001101011000001001 (
b100100001001101011000001001 0
b1001 )
b1001 1
0%
#525000
1%
#526000
b1 4
b1001 3
0&
#530000
b1000000100010010101111010000001 !
b1000000100010010101111010000001 /
b1 $
b1 -
b100100001001101011000001001 "
b100100001001101011000001001 .
b1001 #
b1001 ,
0%
#531000
b110001111100000101011001100011 7
b11 6
b110001111100000101011001100011 9
b11 8
b11 ;
b1001 :
b101001 +
#535000
1%
#540000
1&
b110001111100000101011001100011 (
b110001111100000101011001100011 0
b11 )
b11 1
0%
#545000
1%
#546000
b1001 4
b11 3
0&
#550000
b100100001001101011000001001 !
b100100001001101011000001001 /
b1001 $
b1001 -
b110001111100000101011001100011 "
b110001111100000101011001100011 .
b11 #
b11 ,
0%
#551000
b10000110101110010111101100001101 7
b1101 6
b10000110101110010111101100001101 9
b1101 8
b100 ;
b11 :
b101010 +
#555000
1%
#560000
1&
b10000110101110010111101100001101 (
b10000110101110010111101100001101 0
b1101 )
b1101 1
0%
#565000
1%
#566000
b11 4
b1101 3
0&
#570000
b110001111100000101011001100011 !
b110001111100000101011001100011 /
b11 $
b11 -
b10000110101110010111101100001101 "
b10000110101110010111101100001101 .
b1101 #
b1101 ,
0%
#571000
b11000110110111111001100110001101 7
b11000110110111111001100110001101 9
b101 ;
b1101 :
b101011 +
#575000
1%
#580000
1&
b11000110110111111001100110001101 (
b11000110110111111001100110001101 0
0%
#585000
b11000110110111111001100110001101 "
b11000110110111111001100110001101 .
1%
#586000
b1101 4
0&
#590000
b11000110110111111001100110001101 !
b11000110110111111001100110001101 /
b1101 $
b1101 -
0%
#591000
b110010110000101000010001100101 7
b101 6
b110010110000101000010001100101 9
b101 8
b110 ;
b101100 +
#595000
1%
#600000
1&
b110010110000101000010001100101 (
b110010110000101000010001100101 0
b101 )
b101 1
0%
#605000
1%
#606000
b101 3
0&
#610000
b110010110000101000010001100101 "
b110010110000101000010001100101 .
b101 #
b101 ,
0%
#611000
b1001001101110101001000010010 7
b10010 6
b1001001101110101001000010010 9
b10010 8
b111 ;
b101 :
b101101 +
#615000
1%
#620000
1&
b1001001101110101001000010010 (
b1001001101110101001000010010 0
b10010 )
b10010 1
0%
#625000
1%
#626000
b101 4
b10010 3
0&
#630000
b110010110000101000010001100101 !
b110010110000101000010001100101 /
b101 $
b101 -
b1001001101110101001000010010 "
b1001001101110101001000010010 .
b10010 #
b10010 ,
0%
#631000
b10000000111100111110001100000001 7
b1 6
b10000000111100111110001100000001 9
b1 8
b1000 ;
b10010 :
b101110 +
#635000
1%
#640000
1&
b10000000111100111110001100000001 (
b10000000111100111110001100000001 0
b1 )
b1 1
0%
#645000
1%
#646000
b10010 4
b1 3
0&
#650000
b1001001101110101001000010010 !
b1001001101110101001000010010 /
b10010 $
b10010 -
b10000000111100111110001100000001 "
b10000000111100111110001100000001 .
b1 #
b1 ,
0%
#651000
b10000110110101111100110100001101 7
b1101 6
b10000110110101111100110100001101 9
b1101 8
b1001 ;
b1 :
b101111 +
#655000
1%
#660000
1&
b10000110110101111100110100001101 (
b10000110110101111100110100001101 0
b1101 )
b1101 1
0%
#665000
1%
#666000
b1 4
b1101 3
0&
#670000
b10000000111100111110001100000001 !
b10000000111100111110001100000001 /
b1 $
b1 -
b10000110110101111100110100001101 "
b10000110110101111100110100001101 .
b1101 #
b1101 ,
0%
#671000
b10111011001000111111000101110110 7
b10110 6
b10111011001000111111000101110110 9
b10110 8
b1010 ;
b1101 :
b110000 +
#675000
1%
#680000
1&
b10111011001000111111000101110110 (
b10111011001000111111000101110110 0
b10110 )
b10110 1
0%
#685000
1%
#686000
b1101 4
b10110 3
0&
#690000
b10000110110101111100110100001101 !
b10000110110101111100110100001101 /
b1101 $
b1101 -
b10111011001000111111000101110110 "
b10111011001000111111000101110110 .
b10110 #
b10110 ,
0%
#691000
b10011110100011011100110100111101 7
b11101 6
b10011110100011011100110100111101 9
b11101 8
b1011 ;
b10110 :
b110001 +
#695000
1%
#700000
1&
b10011110100011011100110100111101 (
b10011110100011011100110100111101 0
b11101 )
b11101 1
0%
#705000
1%
#706000
b10110 4
b11101 3
0&
#710000
b10111011001000111111000101110110 !
b10111011001000111111000101110110 /
b10110 $
b10110 -
b10011110100011011100110100111101 "
b10011110100011011100110100111101 .
b11101 #
b11101 ,
0%
#711000
b11110110110101000101011111101101 7
b1101 6
b11110110110101000101011111101101 9
b1101 8
b1100 ;
b11101 :
b110010 +
#715000
1%
#720000
1&
b11110110110101000101011111101101 (
b11110110110101000101011111101101 0
b1101 )
b1101 1
0%
#725000
1%
#726000
b11101 4
b1101 3
0&
#730000
b10011110100011011100110100111101 !
b10011110100011011100110100111101 /
b11101 $
b11101 -
b11110110110101000101011111101101 "
b11110110110101000101011111101101 .
b1101 #
b1101 ,
0%
#731000
b11000110001011011111011110001100 7
b1100 6
b11000110001011011111011110001100 9
b1100 8
b1101 ;
b1101 :
b110011 +
#735000
1%
#740000
1&
b11000110001011011111011110001100 (
b11000110001011011111011110001100 0
b1100 )
b1100 1
0%
#745000
1%
#746000
b1101 4
b1100 3
0&
#750000
b11110110110101000101011111101101 !
b11110110110101000101011111101101 /
b1101 $
b1101 -
b11000110001011011111011110001100 "
b11000110001011011111011110001100 .
b1100 #
b1100 ,
0%
#751000
b11111100111111011110100111111001 7
b11001 6
b11111100111111011110100111111001 9
b11001 8
b1110 ;
b1100 :
b110100 +
#755000
1%
#760000
1&
b11111100111111011110100111111001 (
b11111100111111011110100111111001 0
b11001 )
b11001 1
0%
#765000
1%
#766000
b1100 4
b11001 3
0&
#770000
b11000110001011011111011110001100 !
b11000110001011011111011110001100 /
b1100 $
b1100 -
b11111100111111011110100111111001 "
b11111100111111011110100111111001 .
b11001 #
b11001 ,
0%
#771000
b1100011001101110010010011000110 7
b110 6
b1100011001101110010010011000110 9
b110 8
b1111 ;
b11001 :
b110101 +
#775000
1%
#780000
1&
b1100011001101110010010011000110 (
b1100011001101110010010011000110 0
b110 )
b110 1
0%
#785000
1%
#786000
b11001 4
b110 3
0&
#790000
b11111100111111011110100111111001 !
b11111100111111011110100111111001 /
b11001 $
b11001 -
b1100011001101110010010011000110 "
b1100011001101110010010011000110 .
b110 #
b110 ,
0%
#791000
b1100010111101111000010011000101 7
b101 6
b1100010111101111000010011000101 9
b101 8
b10000 ;
b110 :
b110110 +
#795000
1%
#800000
1&
b1100010111101111000010011000101 (
b1100010111101111000010011000101 0
b101 )
b101 1
0%
#805000
1%
#806000
b110 4
b101 3
0&
#810000
b1100011001101110010010011000110 !
b1100011001101110010010011000110 /
b110 $
b110 -
b1100010111101111000010011000101 "
b1100010111101111000010011000101 .
b101 #
b101 ,
0%
#811000
b1010101000100111101001010101010 7
b1010 6
b1010101000100111101001010101010 9
b1010 8
b10001 ;
b101 :
b110111 +
#815000
1%
#820000
1&
b1010101000100111101001010101010 (
b1010101000100111101001010101010 0
b1010 )
b1010 1
0%
#825000
1%
#826000
b101 4
b1010 3
0&
#830000
b1100010111101111000010011000101 !
b1100010111101111000010011000101 /
b101 $
b101 -
b1010101000100111101001010101010 "
b1010101000100111101001010101010 .
b1010 #
b1010 ,
0%
#831000
b11110010101011111111011111100101 7
b101 6
b11110010101011111111011111100101 9
b101 8
b10010 ;
b1010 :
b111000 +
#835000
1%
#840000
1&
b11110010101011111111011111100101 (
b11110010101011111111011111100101 0
b101 )
b101 1
0%
#845000
b11110010101011111111011111100101 !
b11110010101011111111011111100101 /
1%
#846000
b1010 4
b101 3
0&
#850000
b1010101000100111101001010101010 !
b1010101000100111101001010101010 /
b1010 $
b1010 -
b11110010101011111111011111100101 "
b11110010101011111111011111100101 .
b101 #
b101 ,
0%
#851000
b111011110100100111001001110111 7
b10111 6
b111011110100100111001001110111 9
b10111 8
b10011 ;
b101 :
b111001 +
#855000
1%
#860000
1&
b111011110100100111001001110111 (
b111011110100100111001001110111 0
b10111 )
b10111 1
0%
#865000
1%
#866000
b101 4
b10111 3
0&
#870000
b11110010101011111111011111100101 !
b11110010101011111111011111100101 /
b101 $
b101 -
b111011110100100111001001110111 "
b111011110100100111001001110111 .
b10111 #
b10111 ,
0%
#871000
b1001001100101101011000010010 7
b10010 6
b1001001100101101011000010010 9
b10010 8
b10100 ;
b10111 :
b111010 +
#875000
1%
#880000
1&
b1001001100101101011000010010 (
b1001001100101101011000010010 0
b10010 )
b10010 1
0%
#885000
1%
#886000
b10111 4
b10010 3
0&
#890000
b111011110100100111001001110111 !
b111011110100100111001001110111 /
b10111 $
b10111 -
b1001001100101101011000010010 "
b1001001100101101011000010010 .
b10010 #
b10010 ,
0%
#891000
b11000111111011001101101110001111 7
b1111 6
b11000111111011001101101110001111 9
b1111 8
b10101 ;
b10010 :
b111011 +
#895000
1%
#900000
1&
b11000111111011001101101110001111 (
b11000111111011001101101110001111 0
b1111 )
b1111 1
0%
#905000
1%
#906000
b10010 4
b1111 3
0&
#910000
b1001001100101101011000010010 !
b1001001100101101011000010010 /
b10010 $
b10010 -
b11000111111011001101101110001111 "
b11000111111011001101101110001111 .
b1111 #
b1111 ,
0%
#911000
b11111001001100000110100111110010 7
b10010 6
b11111001001100000110100111110010 9
b10010 8
b10110 ;
b1111 :
b111100 +
#915000
1%
#920000
1&
b11111001001100000110100111110010 (
b11111001001100000110100111110010 0
b10010 )
b10010 1
0%
#925000
b11111001001100000110100111110010 !
b11111001001100000110100111110010 /
1%
#926000
b1111 4
b10010 3
0&
#930000
b11000111111011001101101110001111 !
b11000111111011001101101110001111 /
b1111 $
b1111 -
b11111001001100000110100111110010 "
b11111001001100000110100111110010 .
b10010 #
b10010 ,
0%
#931000
b1100111011101101001011011001110 7
b1110 6
b1100111011101101001011011001110 9
b1110 8
b10111 ;
b10010 :
b111101 +
#935000
1%
#940000
1&
b1100111011101101001011011001110 (
b1100111011101101001011011001110 0
b1110 )
b1110 1
0%
#945000
1%
#946000
b10010 4
b1110 3
0&
#950000
b11111001001100000110100111110010 !
b11111001001100000110100111110010 /
b10010 $
b10010 -
b1100111011101101001011011001110 "
b1100111011101101001011011001110 .
b1110 #
b1110 ,
0%
#951000
b1110100000000000111101011101000 7
b1000 6
b1110100000000000111101011101000 9
b1000 8
b11000 ;
b1110 :
b111110 +
#955000
1%
#960000
1&
b1110100000000000111101011101000 (
b1110100000000000111101011101000 0
b1000 )
b1000 1
0%
#965000
1%
#966000
b1110 4
b1000 3
0&
#970000
b1100111011101101001011011001110 !
b1100111011101101001011011001110 /
b1110 $
b1110 -
b1110100000000000111101011101000 "
b1110100000000000111101011101000 .
b1000 #
b1000 ,
0%
#971000
b1100010110010100100111011000101 7
b101 6
b1100010110010100100111011000101 9
b101 8
b11001 ;
b1000 :
b111111 +
#975000
1%
#980000
1&
b1100010110010100100111011000101 (
b1100010110010100100111011000101 0
b101 )
b101 1
0%
#985000
1%
#986000
b1000 4
b101 3
0&
#990000
b1110100000000000111101011101000 !
b1110100000000000111101011101000 /
b1000 $
b1000 -
b1100010110010100100111011000101 "
b1100010110010100100111011000101 .
b101 #
b101 ,
0%
#991000
b10101110010110000100100101011100 7
b11100 6
b10101110010110000100100101011100 9
b11100 8
b11010 ;
b101 :
b1000000 +
#995000
1%
#1000000
1&
b10101110010110000100100101011100 (
b10101110010110000100100101011100 0
b11100 )
b11100 1
0%
#1005000
1%
#1006000
b101 4
b11100 3
0&
#1010000
b1100010110010100100111011000101 !
b1100010110010100100111011000101 /
b101 $
b101 -
b10101110010110000100100101011100 "
b10101110010110000100100101011100 .
b11100 #
b11100 ,
0%
#1011000
b1011110100011100010100010111101 7
b11101 6
b1011110100011100010100010111101 9
b11101 8
b11011 ;
b11100 :
b1000001 +
#1015000
1%
#1020000
1&
b1011110100011100010100010111101 (
b1011110100011100010100010111101 0
b11101 )
b11101 1
0%
#1025000
1%
#1026000
b11100 4
b11101 3
0&
#1030000
b10101110010110000100100101011100 !
b10101110010110000100100101011100 /
b11100 $
b11100 -
b1011110100011100010100010111101 "
b1011110100011100010100010111101 .
b11101 #
b11101 ,
0%
#1031000
b10110101010110101100000101101 7
b1101 6
b10110101010110101100000101101 9
b1101 8
b11100 ;
b11101 :
b1000010 +
#1035000
1%
#1040000
1&
b10110101010110101100000101101 (
b10110101010110101100000101101 0
b1101 )
b1101 1
0%
#1045000
1%
#1046000
b11101 4
b1101 3
0&
#1050000
b1011110100011100010100010111101 !
b1011110100011100010100010111101 /
b11101 $
b11101 -
b10110101010110101100000101101 "
b10110101010110101100000101101 .
b1101 #
b1101 ,
0%
#1051000
b110010101001110010011001100101 7
b101 6
b110010101001110010011001100101 9
b101 8
b11101 ;
b1101 :
b1000011 +
#1055000
1%
#1060000
1&
b110010101001110010011001100101 (
b110010101001110010011001100101 0
b101 )
b101 1
0%
#1065000
1%
#1066000
b1101 4
b101 3
0&
#1070000
b10110101010110101100000101101 !
b10110101010110101100000101101 /
b1101 $
b1101 -
b110010101001110010011001100101 "
b110010101001110010011001100101 .
b101 #
b101 ,
0%
#1071000
b110001111011110110001001100011 7
b11 6
b110001111011110110001001100011 9
b11 8
b11110 ;
b101 :
b1000100 +
#1075000
1%
#1080000
1&
b110001111011110110001001100011 (
b110001111011110110001001100011 0
b11 )
b11 1
0%
#1085000
1%
#1086000
b101 4
b11 3
0&
#1090000
b110010101001110010011001100101 !
b110010101001110010011001100101 /
b101 $
b101 -
b110001111011110110001001100011 "
b110001111011110110001001100011 .
b11 #
b11 ,
0%
#1091000
b10000101011100111000011100001010 7
b1010 6
b10000101011100111000011100001010 9
b1010 8
b11111 ;
b11 :
b1000101 +
#1095000
1%
#1100000
1&
b10000101011100111000011100001010 (
b10000101011100111000011100001010 0
b1010 )
b1010 1
0%
#1105000
1%
#1106000
b11 4
b1010 3
0&
#1110000
b110001111011110110001001100011 !
b110001111011110110001001100011 /
b11 $
b11 -
b10000101011100111000011100001010 "
b10000101011100111000011100001010 .
b1010 #
b1010 ,
0%
#1111000
b1000000001110110010001010000000 7
b0 6
b1000000001110110010001010000000 9
b0 8
b100000 ;
b1010 :
b1000110 +
#1115000
1%
#1120000
1&
b1000000001110110010001010000000 (
b1000000001110110010001010000000 0
b0 )
b0 1
0%
#1125000
1%
#1126000
b1010 4
b0 3
0&
#1130000
b10000101011100111000011100001010 !
b10000101011100111000011100001010 /
b1010 $
b1010 -
b0 "
b0 .
b0 #
b0 ,
0%
#1131000
b10010000011001000010000100100000 7
b10010000011001000010000100100000 9
b100001 ;
b0 :
b1000111 +
#1135000
1%
#1140000
1&
b10010000011001000010000100100000 (
b10010000011001000010000100100000 0
0%
#1145000
1%
#1146000
b0 4
0&
#1150000
b0 !
b0 /
b0 $
b0 -
0%
#1151000
b11010101011110000100010110101010 7
b1010 6
b11010101011110000100010110101010 9
b1010 8
b100010 ;
b1001000 +
#1155000
1%
#1160000
1&
b11010101011110000100010110101010 (
b11010101011110000100010110101010 0
b1010 )
b1010 1
0%
#1165000
1%
#1166000
b1010 3
0&
#1170000
b11010101011110000100010110101010 "
b11010101011110000100010110101010 .
b1010 #
b1010 ,
0%
#1171000
b1001110110011001100110010011101 7
b11101 6
b1001110110011001100110010011101 9
b11101 8
b100011 ;
b1010 :
b1001001 +
#1175000
1%
#1180000
1&
b1001110110011001100110010011101 (
b1001110110011001100110010011101 0
b11101 )
b11101 1
0%
#1185000
1%
#1186000
b1010 4
b11101 3
0&
